Workbook
Name ListaCargosStd: Precios!$B$2:$B$1023
Name ListaLocales: Locales!$A$2:$A$110
Name ListaMateriales: Precios!$C$2:$C$1023
Name TablaLocales: Locales!$A$1:$B$110
Name TablaMapeoCargos: MapeoCargos!$A$2:$B$1001

Sheet Locales
A1: LOCAL | B1: GRUPO
A2: SAN BORJA | B2: LIMA E ICA PROVINCIA
A3: POLO | B3: LIMA E ICA PROVINCIA
A4: JESUS MARIA | B4: LIMA E ICA PROVINCIA
A5: DOÑA ROSA | B5: LIMA E ICA PROVINCIA
A6: SURCO | B6: LIMA E ICA PROVINCIA
A7: ICA | B7: LIMA E ICA PROVINCIA
A8: ICA PROVINCIA | B8: LIMA E ICA PROVINCIA
A9: DOMINICANA | B9: LIMA E ICA PROVINCIA
A10: LIMA HISTORICO | B10: LIMA E ICA PROVINCIA
A11: FAUCETT | B11: LIMA E ICA PROVINCIA
A12: ALAMEDA | B12: LIMA E ICA PROVINCIA
... A37: SAN ISIDRO | B37: VILLA STEAKHOUSE

Sheet MapeoCargos
A1: CARGO ORIGINAL (del listado) | B1: CARGO ESTANDAR (para precio/uniforme)
A2: MOZO | B2: MOZO
A3: MOZO P/T | B3: MOZO
A4: ENTRENADOR DE SERVICIO | B4: MOZO
A5: MOZO PART TIME | B5: MOZO
A6: AZAFATA | B6: AZAFATA
A7: AZAFATA P/T | B7: AZAFATA
A8: AZAFATA FULL TIME | B8: AZAFATA
A9: PACKER | B9: PACKER
A10: PACKER P/T | B10: PACKER
A11: MOTORIZADO | B11: MOTORIZADO
A12: MOTORIZADO P/T | B12: MOTORIZADO
... A91: COCINERO(A) SALTEADOR | B91: PRODUCCIÓN / COCINA

Sheet Personal
A1: DNI | B1: RAZON SOCIAL | C1: LOCAL | D1: APELLIDOS Y NOMBRES | E1: CARGO ORIGINAL | F1: CARGO ESTANDAR (auto) | G1: FECHA INGRESO | I1: LISTADO DE PERSONAL
A2: 09739137 | B2: VILLA CHICKEN S.A.C. | C2: VCH-ADM | D2: MELGAREJO MEZA ZENOVIO | E2: GERENTE DE OPERACIONES | F2: {=IFERROR(_xlfn.XLOOKUP(E2,MapeoCargos!$A:$A,MapeoCargos!$B:$B,E2),E2)} -> GERENTE DE OPERACIONES | G2: 38842
A3: 28108075 | B3: VILLA CHICKEN S.A.C. | C3: SURCO | D3: FLORES TUCTO SEGUNDO ANDRES | E3: AYUDANTE DE COCINA | F3: {=IFERROR(_xlfn.XLOOKUP(E3,MapeoCargos!$A:$A,MapeoCargos!$B:$B,E3),E3)} -> PRODUCCIÓN / COCINA | G3: 38930
A4: 27559471 | B4: VILLA CHICKEN S.A.C. | C4: SAN BORJA | D4: GUEVARA SILVA JUAN ANIBAL | E4: ADMINISTRADOR(A) | F4: {=IFERROR(_xlfn.XLOOKUP(E4,MapeoCargos!$A:$A,MapeoCargos!$B:$B,E4),E4)} -> STAFF ADMINISTRATIVO | G4: 40026
A5: 40564075 | B5: VILLA CHICKEN S.A.C. | C5: SAN BORJA | D5: LLAMO FERNANDEZ RAMIRO | E5: MOZO | F5: {=IFERROR(_xlfn.XLOOKUP(E5,MapeoCargos!$A:$A,MapeoCargos!$B:$B,E5),E5)} -> MOZO | G5: 40253
A6: 06819776 | B6: VILLA CHICKEN S.A.C. | C6: SAN BORJA | D6: CALDERON ROJAS LEODORO | E6: MOZO | F6: {=IFERROR(_xlfn.XLOOKUP(E6,MapeoCargos!$A:$A,MapeoCargos!$B:$B,E6),E6)} -> MOZO | G6: 40269
A7: 09282806 | B7: VILLA INVEST S.A.C. | C7: VI-ADM | D7: PALIZA BAYLON VICENTE PAUL | E7: SUPERVISOR DE PRODUCCION | F7: {=IFERROR(_xlfn.XLOOKUP(E7,MapeoCargos!$A:$A,MapeoCargos!$B:$B,E7),E7)} -> SUPERVISOR DE PRODUCCION | G7: 40422
A8: 42210873 | B8: VILLA INVEST S.A.C. | C8: EJERCITO | D8: NEYRA RODRIGUEZ DANNY IVAN | E8: HORNERO (A) | F8: {=IFERROR(_xlfn.XLOOKUP(E8,MapeoCargos!$A:$A,MapeoCargos!$B:$B,E8),E8)} -> PRODUCCIÓN / COCINA | G8: 40749
A9: 06446881 | B9: VILLA CHICKEN S.A.C. | C9: VCH-ADM | D9: GOMEZ RIOS ELENA | E9: JEFE DE RECURSOS HUMANOS 2 | F9: {=IFERROR(_xlfn.XLOOKUP(E9,MapeoCargos!$A:$A,MapeoCargos!$B:$B,E9),E9)} -> JEFE DE RECURSOS HUMANOS 2 | G9: 40756
A10: 40706652 | B10: VILLA CHICKEN S.A.C. | C10: SAN BORJA | D10: DIAZ CCALA HUGO | E10: HORNERO (A) | F10: {=IFERROR(_xlfn.XLOOKUP(E10,MapeoCargos!$A:$A,MapeoCargos!$B:$B,E10),E10)} -> PRODUCCIÓN / COCINA | G10: 40969
A11: 06102961 | B11: VILLA INVEST S.A.C. | C11: VI-ADM | D11: CHIN CHAU ROSA | E11: GERENTE GENERAL | F11: {=IFERROR(_xlfn.XLOOKUP(E11,MapeoCargos!$A:$A,MapeoCargos!$B:$B,E11),E11)} -> GERENTE GENERAL | G11: 41031
A12: 48037304 | B12: VILLA INVEST S.A.C. | C12: OLIVOS | D12: ROJAS BAYONA BERUSKA TAMARA | E12: ADMINISTRADOR(A) | F12: {=IFERROR(_xlfn.XLOOKUP(E12,MapeoCargos!$A:$A,MapeoCargos!$B:$B,E12),E12)} -> STAFF ADMINISTRATIVO | G12: 41061
A13: 07783723 | B13: VILLA CHICKEN S.A.C. | C13: VCH-ADM | D13: LAU PEREZ ALFREDO JOSE | E13: ASISTENTE DE GERENCIA | F13: {=IFERROR(_xlfn.XLOOKUP(E13,MapeoCargos!$A:$A,MapeoCargos!$B:$B,E13),E13)} -> ASISTENTE DE GERENCIA | G13: 41061
... A73: 47967370 | B73: VILLA INVEST S.A.C. | C73: SAN MIGUEL | D73: CUTIPA PALOMINO JOSUE ROBERTO | E73: MOTORIZADO | F73: {=IFERROR(_xlfn.XLOOKUP(E73,MapeoCargos!$A:$A,MapeoCargos!$B:$B,E73),E73)} -> MOTORIZADO | G73: 42826
A74: 72511903 | B74: VILLA INVEST S.A.C. | C74: EJERCITO | D74: PANANA NAJARRO LUIS ENRIQUE | E74: MOTORIZADO | F74: {=IFERROR(_xlfn.XLOOKUP(E74,MapeoCargos!$A:$A,MapeoCargos!$B:$B,E74),E74)} -> MOTORIZADO | G74: 45901 | H74: AGREGADO DEL LISTADO DE PERSONAL DE OCTUBRE
A75: 45728123 | B75: VILLA CHICKEN S.A.C. | C75: SAN BORJA | D75: DIAZ ESTELA ENRIQUE | E75: MOTORIZADO | F75: {=IFERROR(_xlfn.XLOOKUP(E75,MapeoCargos!$A:$A,MapeoCargos!$B:$B,E75),E75)} -> MOTORIZADO | G75: 42826
A76: 47247086 | B76: VILLA CHICKEN S.A.C. | C76: VCH-ADM | D76: PINEDO JULCA GEINER OMAR | E76: SUPERVISOR DE OPERACIONES | F76: {=IFERROR(_xlfn.XLOOKUP(E76,MapeoCargos!$A:$A,MapeoCargos!$B:$B,E76),E76)} -> SUPERVISOR DE OPERACIONES | G76: 42856
A77: 44449260 | B77: VILLA CHICKEN S.A.C. | C77: ICA | D77: ARELLANO MUÑOZ GEORGE JOEL | E77: HORNERO (A) | F77: {=IFERROR(_xlfn.XLOOKUP(E77,MapeoCargos!$A:$A,MapeoCargos!$B:$B,E77),E77)} -> PRODUCCIÓN / COCINA | G77: 42856
A78: 41185109 | B78: FOOD & BEVERAGE INVEST S.A.C. | C78: HACIENDA | D78: QUIROZ CAPCHA MAXIMO | E78: PARRILLERO (A) | F78: {=IFERROR(_xlfn.XLOOKUP(E78,MapeoCargos!$A:$A,MapeoCargos!$B:$B,E78),E78)} -> PRODUCCIÓN / COCINA | G78: 42887
A79: 43965735 | B79: VILLA CHICKEN S.A.C. | C79: ICA | D79: LEVANO TASAYCO ROBERTO JAVIER | E79: HORNERO (A) | F79: {=IFERROR(_xlfn.XLOOKUP(E79,MapeoCargos!$A:$A,MapeoCargos!$B:$B,E79),E79)} -> PRODUCCIÓN / COCINA | G79: 42887
A80: 09491742 | B80: VILLA CHICKEN S.A.C. | C80: SURCO | D80: VILLAR RAMOS JOSE ANTONIO | E80: ADMINISTRADOR(A) | F80: {=IFERROR(_xlfn.XLOOKUP(E80,MapeoCargos!$A:$A,MapeoCargos!$B:$B,E80),E80)} -> STAFF ADMINISTRATIVO | G80: 42902
A81: 45038734 | B81: VILLA CHICKEN S.A.C. | C81: POLO | D81: PEZO LOPEZ SOFIA ISABEL | E81: CAJERO (A) | F81: {=IFERROR(_xlfn.XLOOKUP(E81,MapeoCargos!$A:$A,MapeoCargos!$B:$B,E81),E81)} -> CAJA | G81: 42917
A82: 43191410 | B82: FOOD & BEVERAGE INVEST S.A.C. | C82: MAGDALENA | D82: CAJUSOL SANJINEZ WILLY FRANKLIN | E82: PARRILLERO (A) | F82: {=IFERROR(_xlfn.XLOOKUP(E82,MapeoCargos!$A:$A,MapeoCargos!$B:$B,E82),E82)} -> PRODUCCIÓN / COCINA | G82: 42963
A83: 07538742 | B83: VILLA CHICKEN S.A.C. | C83: POLO | D83: HUAMANI SACSI MARIA LUISA | E83: AUXILIAR DE LIMPIEZA | F83: {=IFERROR(_xlfn.XLOOKUP(E83,MapeoCargos!$A:$A,MapeoCargos!$B:$B,E83),E83)} -> LIMPIEZA / MANTENIMIENTO | G83: 43009
A84: 49097756 | B84: FOOD & BEVERAGE INVEST S.A.C. | C84: F&B-ADM | D84: SIMANCA REYES JOSE ALEJANDRO | E84: COORDINADOR DE MANTENIMIENTO | F84: {=IFERROR(_xlfn.XLOOKUP(E84,MapeoCargos!$A:$A,MapeoCargos!$B:$B,E84),E84)} -> COORDINADOR DE MANTENIMIENTO | G84: 43032
A85: 49003395 | B85: FOOD & BEVERAGE INVEST S.A.C. | C85: F&B-ADM | D85: KONG BARRIOS DANIELA ROSA | E85: COMMUNITY MANAGER | F85: {=IFERROR(_xlfn.XLOOKUP(E85,MapeoCargos!$A:$A,MapeoCargos!$B:$B,E85),E85)} -> COMMUNITY MANAGER | G85: 43032
A86: 41855846 | B86: VILLA CHICKEN S.A.C. | C86: SAN BORJA | D86: VILCA ROJAS PEDRO YULIO | E86: MOTORIZADO | F86: {=IFERROR(_xlfn.XLOOKUP(E86,MapeoCargos!$A:$A,MapeoCargos!$B:$B,E86),E86)} -> MOTORIZADO | G86: 43040
... A375: 72896244 | B375: VILLA INVEST S.A.C. | C375: OLIVOS | D375: YUCRA SANTOS GABRIEL EDUARDO | E375: AUXILIAR DE LIMPIEZA | F375: {=IFERROR(_xlfn.XLOOKUP(E375,MapeoCargos!$A:$A,MapeoCargos!$B:$B,E375),E375)} -> LIMPIEZA / MANTENIMIENTO | G375: 45170
A376: 46722628 | B376: VILLA INVEST S.A.C. | C376: LARCOMAR | D376: REYES RAMIREZ DIANA YOLI | E376: ADMINISTRADOR(A) JUNIOR | F376: {=IFERROR(_xlfn.XLOOKUP(E376,MapeoCargos!$A:$A,MapeoCargos!$B:$B,E376),E376)} -> STAFF ADMINISTRATIVO | G376: 45170 | H376: SALE COMO CAJERO EN EL LISTADO DE PERSONAL
A377: 10882142 | B377: VILLA CHICKEN S.A.C. | C377: JESUS MARIA | D377: GRANADOS MORA JENNY MERCEDES | E377: AUXILIAR DE LIMPIEZA | F377: {=IFERROR(_xlfn.XLOOKUP(E377,MapeoCargos!$A:$A,MapeoCargos!$B:$B,E377),E377)} -> LIMPIEZA / MANTENIMIENTO | G377: 45181
A378: 45983609 | B378: VILLA INVEST S.A.C. | C378: NAVARRETE | D378: ANICAMA PIÑA RUFFO ENRIQUE | E378: CAJERO (A) | F378: {=IFERROR(_xlfn.XLOOKUP(E378,MapeoCargos!$A:$A,MapeoCargos!$B:$B,E378),E378)} -> CAJA | G378: 45181
A379: 47726715 | B379: VILLA CHICKEN S.A.C. | C379: HISTORICO | D379: LACHOS RIVERA JOSE MANUEL | E379: SEGURIDAD | F379: {=IFERROR(_xlfn.XLOOKUP(E379,MapeoCargos!$A:$A,MapeoCargos!$B:$B,E379),E379)} -> SEGURIDAD | G379: 45181
A380: 46007144 | B380: VILLA CHICKEN S.A.C. | C380: VCH-ADM | D380: CARPIO FERREYRA JERICO ANDRES | E380: GERENTE DE MARKETING | F380: {=IFERROR(_xlfn.XLOOKUP(E380,MapeoCargos!$A:$A,MapeoCargos!$B:$B,E380),E380)} -> GERENTE DE MARKETING | G380: 45187
A381: 44265083 | B381: VILLA CHICKEN S.A.C. | C381: SURCO | D381: IZUISA PEREZ KERVIN | E381: HORNERO (A) | F381: {=IFERROR(_xlfn.XLOOKUP(E381,MapeoCargos!$A:$A,MapeoCargos!$B:$B,E381),E381)} -> PRODUCCIÓN / COCINA | G381: 45195
A382: 47008833 | B382: VILLA CHICKEN S.A.C. | C382: ICA | D382: VARGAS FERNANDEZ JAHIR ALESSANDRO | E382: ADMINISTRADOR(A) | F382: {=IFERROR(_xlfn.XLOOKUP(E382,MapeoCargos!$A:$A,MapeoCargos!$B:$B,E382),E382)} -> STAFF ADMINISTRATIVO | G382: 45200
A383: 74530037 | B383: VILLA CHICKEN S.A.C. | C383: SURCO | D383: REGALADO BELLIDO MICAL ZOE | E383: AZAFATA | F383: {=IFERROR(_xlfn.XLOOKUP(E383,MapeoCargos!$A:$A,MapeoCargos!$B:$B,E383),E383)} -> AZAFATA | G383: 45202
A384: 72196501 | B384: VILLA CHICKEN S.A.C. | C384: HISTORICO | D384: MARTINEZ OSORES LUIS ENRIQUE | E384: MOZO P/T | F384: {=IFERROR(_xlfn.XLOOKUP(E384,MapeoCargos!$A:$A,MapeoCargos!$B:$B,E384),E384)} -> MOZO | G384: 45202
A385: 74713457 | B385: FOOD & BEVERAGE INVEST S.A.C. | C385: F&B-CALL | D385: ASIAN ÑAUPA MAYRA BELEN | E385: TELEOPERADOR (A) P/T | F385: {=IFERROR(_xlfn.XLOOKUP(E385,MapeoCargos!$A:$A,MapeoCargos!$B:$B,E385),E385)} -> TELEOPERADOR (A) P/T | G385: 45209
A386: 42500135 | B386: FOOD & BEVERAGE INVEST S.A.C. | C386: F&B-CALL | D386: GUTIERREZ SALCEDO NOELIA JAZMIN | E386: TELEOPERADOR (A) P/T | F386: {=IFERROR(_xlfn.XLOOKUP(E386,MapeoCargos!$A:$A,MapeoCargos!$B:$B,E386),E386)} -> TELEOPERADOR (A) P/T | G386: 45209
A387: 72021148 | B387: FOOD & BEVERAGE INVEST S.A.C. | C387: F&B-ADM | D387: HURTADO FALCON LENIN ROSSELL | E387: AUDITOR DE CALIDAD | F387: {=IFERROR(_xlfn.XLOOKUP(E387,MapeoCargos!$A:$A,MapeoCargos!$B:$B,E387),E387)} -> AUDITOR DE CALIDAD | G387: 45223
A388: 42131871 | B388: FOOD & BEVERAGE INVEST S.A.C. | C388: MIRAFLORES | D388: SANDOVAL FREITAS JORGE CARLOS | E388: MOTORIZADO | F388: {=IFERROR(_xlfn.XLOOKUP(E388,MapeoCargos!$A:$A,MapeoCargos!$B:$B,E388),E388)} -> MOTORIZADO | G388: 45231
... A533: 48697550 | B533: FOOD & BEVERAGE INVEST S.A.C. | C533: MOLINA 2 | D533: INGA VALDIVIEZO ANGYE BRIGYT | E533: AZAFATA | F533: {=IFERROR(_xlfn.XLOOKUP(E533,MapeoCargos!$A:$A,MapeoCargos!$B:$B,E533),E533)} -> AZAFATA | G533: 45600
A534: 76460420 | B534: VILLA CHICKEN S.A.C. | C534: ICA | D534: ECOS ROJAS ANDRE ALESSANDRO | E534: BARTENDER | F534: {=IFERROR(_xlfn.XLOOKUP(E534,MapeoCargos!$A:$A,MapeoCargos!$B:$B,E534),E534)} -> BAR | G534: 45965 | H534: AGREGADO DEL LISTADO DE PERSONAL DE NOVIEMBRE
A535: 75549316 | B535: VILLA CHICKEN S.A.C. | C535: SURCO | D535: TELLO MOSTACERO NICK FRANKLIN | E535: BARTENDER | F535: {=IFERROR(_xlfn.XLOOKUP(E535,MapeoCargos!$A:$A,MapeoCargos!$B:$B,E535),E535)} -> BAR | G535: 45600
A536: 45070469 | B536: VILLA CHICKEN S.A.C. | C536: CHORRILLOS REAL PLAZA | D536: MONZON TAPIA RUBEN | E536: ADMINISTRADOR(A) | F536: {=IFERROR(_xlfn.XLOOKUP(E536,MapeoCargos!$A:$A,MapeoCargos!$B:$B,E536),E536)} -> STAFF ADMINISTRATIVO | G536: 45600
A537: 48412240 | B537: VILLA CHICKEN S.A.C. | C537: HISTORICO | D537: NUÑEZ LOPEZ JEAN PAUL BRANDON | E537: AYUDANTE DE COCINA | F537: {=IFERROR(_xlfn.XLOOKUP(E537,MapeoCargos!$A:$A,MapeoCargos!$B:$B,E537),E537)} -> AYUDANTE DE COCINA | G537: 45600
A538: 70097590 | B538: VILLA INVEST S.A.C. | C538: EJERCITO | D538: TORRES COTERA VICTOR ALONSO | E538: MOZO | F538: {=IFERROR(_xlfn.XLOOKUP(E538,MapeoCargos!$A:$A,MapeoCargos!$B:$B,E538),E538)} -> MOZO | G538: 45600
A539: 72670432 | B539: VILLA CHICKEN S.A.C. | C539: LARCOMAR | D539: PAREDES MAGUIÑA HUGO RAFAEL | E539: ADMINISTRADOR(A) | F539: {=IFERROR(_xlfn.XLOOKUP(E539,MapeoCargos!$A:$A,MapeoCargos!$B:$B,E539),E539)} -> STAFF ADMINISTRATIVO | G539: 45607
A540: 71719906 | B540: VILLA CHICKEN S.A.C. | C540: SURCO | D540: MACEDO AMASIFUEN MOISES | E540: MOTORIZADO | F540: {=IFERROR(_xlfn.XLOOKUP(E540,MapeoCargos!$A:$A,MapeoCargos!$B:$B,E540),E540)} -> MOTORIZADO | G540: 45607
A541: 48747298 | B541: VILLA INVEST S.A.C. | C541: SAN MIGUEL | D541: VALENCIA CLAUDIO CRISTIAN JESUS | E541: HORNERO (A) | F541: {=IFERROR(_xlfn.XLOOKUP(E541,MapeoCargos!$A:$A,MapeoCargos!$B:$B,E541),E541)} -> PRODUCCIÓN / COCINA | G541: 45607
A542: 43630753 | B542: VILLA CHICKEN S.A.C. | C542: ICA | D542: INFANTE JARA CINTHIA LORENA | E542: AYUDANTE DE COCINA | F542: {=IFERROR(_xlfn.XLOOKUP(E542,MapeoCargos!$A:$A,MapeoCargos!$B:$B,E542),E542)} -> AYUDANTE DE COCINA | G542: 45607
A543: 47876191 | B543: VILLA CHICKEN S.A.C. | C543: VCH-ADM | D543: MEJIA SEBASTIAN MARTIN ALBERTO | E543: ASISTENTE DE RECURSOS HUMANOS | F543: {=IFERROR(_xlfn.XLOOKUP(E543,MapeoCargos!$A:$A,MapeoCargos!$B:$B,E543),E543)} -> ASISTENTE DE RECURSOS HUMANOS | G543: 45614
A544: 77702834 | B544: VILLA INVEST S.A.C. | C544: OLIVOS | D544: ANGELES BONILLA EVELIA KATHERINE | E544: AZAFATA | F544: {=IFERROR(_xlfn.XLOOKUP(E544,MapeoCargos!$A:$A,MapeoCargos!$B:$B,E544),E544)} -> AZAFATA | G544: 45614
A545: 75381520 | B545: VILLA CHICKEN S.A.C. | C545: DOS DE MAYO | D545: RODRIGUEZ URIARTE KEVIN | E545: AYUDANTE DE COCINA | F545: {=IFERROR(_xlfn.XLOOKUP(E545,MapeoCargos!$A:$A,MapeoCargos!$B:$B,E545),E545)} -> AYUDANTE DE COCINA | G545: 45614
A546: 70041037 | B546: VILLA INVEST S.A.C. | C546: OLIVOS | D546: LOPEZ CORO EDINSON ALONSO | E546: MOTORIZADO | F546: {=IFERROR(_xlfn.XLOOKUP(E546,MapeoCargos!$A:$A,MapeoCargos!$B:$B,E546),E546)} -> MOTORIZADO | G546: 45614
... A1147: 73976369 | B1147: STARCAFE PERU S.A.C | C1147: PF - HISTORICO | D1147: MORALES MARTINEZ BARBRA FELIJOS | E1147: COCINERO(A) | F1147: {=IFERROR(_xlfn.XLOOKUP(E1147,MapeoCargos!$A:$A,MapeoCargos!$B:$B,E1147),E1147)} -> PRODUCCIÓN / COCINA | G1147: 45817
A1148: 77624192 | B1148: STARCAFE PERU S.A.C | C1148: LUCKY SEVEN | D1148: GARAY LAZO JHORDAN ANDRE | E1148: AUXILIAR DE LIMPIEZA | F1148: {=IFERROR(_xlfn.XLOOKUP(E1148,MapeoCargos!$A:$A,MapeoCargos!$B:$B,E1148),E1148)} -> LIMPIEZA / MANTENIMIENTO | G1148: 01/07/2025
A1149: 46645623 | B1149: STARCAFE PERU S.A.C | C1149: PF - ADM | D1149: CHING FLORES ANA SOFIA | E1149: ATENCION AL CLIENTE P/T | F1149: {=IFERROR(_xlfn.XLOOKUP(E1149,MapeoCargos!$A:$A,MapeoCargos!$B:$B,E1149),E1149)} -> ATENCION AL CLIENTE P/T | G1149: 01/07/2025
A1150: 003488192 | B1150: STARCAFE PERU S.A.C | C1150: PF - ADM | D1150: FRANCO NIETO LUIS MANUEL | E1150: ASISTENTE DE COMPRAS | F1150: {=IFERROR(_xlfn.XLOOKUP(E1150,MapeoCargos!$A:$A,MapeoCargos!$B:$B,E1150),E1150)} -> ASISTENTE DE COMPRAS | G1150: 01/07/2025
A1151: 73705602 | B1151: STARCAFE PERU S.A.C | C1151: PF - HISTORICO | D1151: BARRIGA BANDINI RENATO LUCIANO | E1151: MOZO | F1151: {=IFERROR(_xlfn.XLOOKUP(E1151,MapeoCargos!$A:$A,MapeoCargos!$B:$B,E1151),E1151)} -> MOZO | G1151: 01/07/2025
A1152: 76270213 | B1152: STARCAFE PERU S.A.C | C1152: PF - SUR | D1152: FRIAS CLEMENTE DANIELA SOFIA | E1152: COUNTER | F1152: {=IFERROR(_xlfn.XLOOKUP(E1152,MapeoCargos!$A:$A,MapeoCargos!$B:$B,E1152),E1152)} -> COUNTER | G1152: 01/07/2025
A1153: 76612699 | B1153: STARCAFE PERU S.A.C | C1153: PF - TAMBO | D1153: PANDURO SILVA MONICA ALMENDRA | E1153: COUNTER | F1153: {=IFERROR(_xlfn.XLOOKUP(E1153,MapeoCargos!$A:$A,MapeoCargos!$B:$B,E1153),E1153)} -> COUNTER | G1153: 45845
A1154: 74083114 | B1154: STARCAFE PERU S.A.C | C1154: PF - HISTORICO | D1154: PAREJA CISNEROS JORGE LUIS ANTONIO | E1154: BARTENDER | F1154: {=IFERROR(_xlfn.XLOOKUP(E1154,MapeoCargos!$A:$A,MapeoCargos!$B:$B,E1154),E1154)} -> BAR | G1154: 45849
A1155: 73081071 | B1155: STARCAFE PERU S.A.C | C1155: PF - TAMBO | D1155: LAZARTE DAMIAN CARLOS ANDRES | E1155: CORREDOR(A) | F1155: {=IFERROR(_xlfn.XLOOKUP(E1155,MapeoCargos!$A:$A,MapeoCargos!$B:$B,E1155),E1155)} -> CORREDOR | G1155: 45856
A1156: 72682900 | B1156: STARCAFE PERU S.A.C | C1156: PF - MOLINA | D1156: SILVA PALACIOS CESAR AUGUSTO | E1156: MOZO | F1156: {=IFERROR(_xlfn.XLOOKUP(E1156,MapeoCargos!$A:$A,MapeoCargos!$B:$B,E1156),E1156)} -> MOZO | G1156: 45856
A1157: 74333178 | B1157: STARCAFE PERU S.A.C | C1157: PF - TAMBO | D1157: FLORES MARTINEZ KIARA JIMENA | E1157: CORREDOR(A) | F1157: {=IFERROR(_xlfn.XLOOKUP(E1157,MapeoCargos!$A:$A,MapeoCargos!$B:$B,E1157),E1157)} -> CORREDOR | G1157: 45859
A1158: 72725467 | B1158: STARCAFE PERU S.A.C | C1158: PF - HISTORICO | D1158: SALCEDO MORALES RODRIGO ISMAEL | E1158: MOZO | F1158: {=IFERROR(_xlfn.XLOOKUP(E1158,MapeoCargos!$A:$A,MapeoCargos!$B:$B,E1158),E1158)} -> MOZO | G1158: 45859
A1159: 43745234 | B1159: STARCAFE PERU S.A.C | C1159: LUCKY SEVEN | D1159: RIVERA HUAYTA JESSICA JEYMI | E1159: AYUDANTE DE COCINA | F1159: {=IFERROR(_xlfn.XLOOKUP(E1159,MapeoCargos!$A:$A,MapeoCargos!$B:$B,E1159),E1159)} -> PRODUCCIÓN / COCINA | G1159: 45870
A1160: 73203439 | B1160: STARCAFE PERU S.A.C | C1160: PF - TAMBO | D1160: CORONADO MENDOZA ANDERSON ARTURO | E1160: AYUDANTE DE COCINA | F1160: {=IFERROR(_xlfn.XLOOKUP(E1160,MapeoCargos!$A:$A,MapeoCargos!$B:$B,E1160),E1160)} -> PRODUCCIÓN / COCINA | G1160: 45870
A1161: 70336053 | B1161: STARCAFE PERU S.A.C | C1161: PF - ADM | D1161: VALENZUELA ALARCON ALEXANDER EMILIO | E1161: CHEF DE PRODUCCIÓN | F1161: {=IFERROR(_xlfn.XLOOKUP(E1161,MapeoCargos!$A:$A,MapeoCargos!$B:$B,E1161),E1161)} -> CHEF DE PRODUCCIÓN | G1161: 45870
A1162: 47395331 | B1162: STARCAFE PERU S.A.C | C1162: PF - DOMINICANA | D1162: BRAVO DESIGLIOLI STTEFANY NICOLL | E1162: COCINERO(A) | F1162: {=IFERROR(_xlfn.XLOOKUP(E1162,MapeoCargos!$A:$A,MapeoCargos!$B:$B,E1162),E1162)} -> PRODUCCIÓN / COCINA | G1162: 45870
A1163: 71423279 | B1163: STARCAFE PERU S.A.C | C1163: PF - MOLINA | D1163: ANDIA OSIS ANGELA | E1163: AZAFATA | F1163: {=IFERROR(_xlfn.XLOOKUP(E1163,MapeoCargos!$A:$A,MapeoCargos!$B:$B,E1163),E1163)} -> AZAFATA | G1163: 45870
A1164: 74733940 | B1164: STARCAFE PERU S.A.C | C1164: PF - MOLINA | D1164: ALCARRAZ GUIZADO CARLO ANDRE | E1164: MOZO P/T | F1164: {=IFERROR(_xlfn.XLOOKUP(E1164,MapeoCargos!$A:$A,MapeoCargos!$B:$B,E1164),E1164)} -> MOZO | G1164: 45870
... A1710: 40826429 | B1710: GOLDEN TAMBO INVERSIONES S.A.C. | C1710: TAMBO - CASA GRAÑA | D1710: FERRAND CASTILLO GONZALO | E1710: CHEF EJECUTIVO | F1710: {=IFERROR(_xlfn.XLOOKUP(E1710,MapeoCargos!$A:$A,MapeoCargos!$B:$B,E1710),E1710)} -> CHEF EJECUTIVO | G1710: 45831
A1711: 75056912 | B1711: GOLDEN TAMBO INVERSIONES S.A.C. | C1711: TAMBO - PLAZA MERCADO | D1711: ESCALANTE ABAD VERONICA ANDREA | E1711: CAJERO(A) | F1711: {=IFERROR(_xlfn.XLOOKUP(E1711,MapeoCargos!$A:$A,MapeoCargos!$B:$B,E1711),E1711)} -> CAJA | G1711: 01/07/2025
A1712: 75157591 | B1712: GOLDEN TAMBO INVERSIONES S.A.C. | C1712: LA TAPADA - ADM | D1712: TORRES BOGGIANO DINA YHIARA ISABEL | E1712: ASISTENTE DE GESTION Y CONTROL ADMINISTRATIVO | F1712: {=IFERROR(_xlfn.XLOOKUP(E1712,MapeoCargos!$A:$A,MapeoCargos!$B:$B,E1712),E1712)} -> ASISTENTE DE GESTION Y CONTROL ADMINISTRATIVO | G1712: 01/07/2025
A1713: 72472031 | B1713: GOLDEN TAMBO INVERSIONES S.A.C. | C1713: TAMBO - PLAZA MERCADO | D1713: GUTIERREZ ORE CHRISTOPHER ALEJANDRO | E1713: AYUDANTE DE COCINA | F1713: {=IFERROR(_xlfn.XLOOKUP(E1713,MapeoCargos!$A:$A,MapeoCargos!$B:$B,E1713),E1713)} -> PRODUCCIÓN / COCINA | G1713: 45845
A1714: 71263611 | B1714: GOLDEN TAMBO INVERSIONES S.A.C. | C1714: TAMBO - PLAZA MERCADO | D1714: BENAVIDES DE LA CRUZ WILLIAM ENRIQUE | E1714: COCINERO (A) | F1714: {=IFERROR(_xlfn.XLOOKUP(E1714,MapeoCargos!$A:$A,MapeoCargos!$B:$B,E1714),E1714)} -> COCINERO (A) | G1714: 45845
A1715: 41730175 | B1715: GOLDEN TAMBO INVERSIONES S.A.C. | C1715: TAMBO - PLAZA MERCADO | D1715: TORRES CAJACURI EDINSON RONALD | E1715: CORREDOR(A) | F1715: {=IFERROR(_xlfn.XLOOKUP(E1715,MapeoCargos!$A:$A,MapeoCargos!$B:$B,E1715),E1715)} -> CORREDOR | G1715: 45847
A1716: 72715408 | B1716: GOLDEN TAMBO INVERSIONES S.A.C. | C1716: TAMBO - PLAZA MERCADO | D1716: SAAVEDRA CONDORI ARIANA ANTUANET | E1716: CORREDOR(A) | F1716: {=IFERROR(_xlfn.XLOOKUP(E1716,MapeoCargos!$A:$A,MapeoCargos!$B:$B,E1716),E1716)} -> CORREDOR | G1716: 45849
A1717: 75517819 | B1717: GOLDEN TAMBO INVERSIONES S.A.C. | C1717: TAMBO - PLAZA MERCADO | D1717: ANTAYHUA LUJAN JUAN JESUS ANDRE | E1717: CORREDOR(A) | F1717: {=IFERROR(_xlfn.XLOOKUP(E1717,MapeoCargos!$A:$A,MapeoCargos!$B:$B,E1717),E1717)} -> CORREDOR | G1717: 45849
A1718: 72452395 | B1718: GOLDEN TAMBO INVERSIONES S.A.C. | C1718: LA TAPADA | D1718: MACEDO AVALOS ARIANA NICOLE | E1718: PASTELERO(A) | F1718: {=IFERROR(_xlfn.XLOOKUP(E1718,MapeoCargos!$A:$A,MapeoCargos!$B:$B,E1718),E1718)} -> PASTELERO(A) | G1718: 45859
A1719: 77676069 | B1719: GOLDEN TAMBO INVERSIONES S.A.C. | C1719: TAMBO - PLAZA MERCADO | D1719: ALBINO MAMANI OMAR ANTHONY | E1719: CORREDOR (A) | F1719: {=IFERROR(_xlfn.XLOOKUP(E1719,MapeoCargos!$A:$A,MapeoCargos!$B:$B,E1719),E1719)} -> CORREDOR (A) | G1719: 45870
A1720: 46020665 | B1720: GOLDEN TAMBO INVERSIONES S.A.C. | C1720: TAMBO - CASA GRAÑA | D1720: MORA PANIAGUA CRISTHIANS JESUS | E1720: CHEF EJECUTIVO | F1720: {=IFERROR(_xlfn.XLOOKUP(E1720,MapeoCargos!$A:$A,MapeoCargos!$B:$B,E1720),E1720)} -> CHEF EJECUTIVO | G1720: 45870
A1721: 74903308 | B1721: GOLDEN TAMBO INVERSIONES S.A.C. | C1721: LA TAPADA | D1721: DOMINGUEZ JARA KATHERINE DEBORA | E1721: COORDINADOR (A) DE PASTELERIA | F1721: {=IFERROR(_xlfn.XLOOKUP(E1721,MapeoCargos!$A:$A,MapeoCargos!$B:$B,E1721),E1721)} -> COORDINADOR (A) DE PASTELERIA | G1721: 45870
A1722: 10815257 | B1722: GOLDEN TAMBO INVERSIONES S.A.C. | C1722: TAMBO - PLAZA MERCADO | D1722: SILVA MAMANI ROLANDO NINO | E1722: MANTENIMIENTO | F1722: {=IFERROR(_xlfn.XLOOKUP(E1722,MapeoCargos!$A:$A,MapeoCargos!$B:$B,E1722),E1722)} -> MANTENIMIENTO | G1722: 45880
A1723: 47626127 | B1723: GOLDEN TAMBO INVERSIONES S.A.C. | C1723: TAMBO - PLAZA MERCADO | D1723: ISASI LUDEÑA JULIO RAFAEL | E1723: COCINERO(A) | F1723: {=IFERROR(_xlfn.XLOOKUP(E1723,MapeoCargos!$A:$A,MapeoCargos!$B:$B,E1723),E1723)} -> PRODUCCIÓN / COCINA | G1723: 45887
A1724: 75760518 | B1724: GOLDEN TAMBO INVERSIONES S.A.C. | C1724: LA TAPADA | D1724: PAUCAR MAMANI LUCERO | E1724: AZAFATA | F1724: {=IFERROR(_xlfn.XLOOKUP(E1724,MapeoCargos!$A:$A,MapeoCargos!$B:$B,E1724),E1724)} -> AZAFATA | G1724: 45887
... A1894: 22506607 | B1894: ABASTECEDORA ALIMENTICIA S.A.C. | C1894: ABASTECEDORA ALIMENTICIA | D1894: CRISTOBAL RAMIREZ, RAUL KLEBER | E1894: PRODUCCION DE CREMAS | F1894: {=IFERROR(_xlfn.XLOOKUP(E1894,MapeoCargos!$A:$A,MapeoCargos!$B:$B,E1894),E1894)} -> PRODUCCION DE CREMAS | G1894: 43891
A1895: 45306069 | B1895: ABASTECEDORA ALIMENTICIA S.A.C. | C1895: ABASTECEDORA ALIMENTICIA | D1895: MOROTE VICAÑA, WALTHER | E1895: CONDUCTOR/ASIST. DE GERENCIA | F1895: {=IFERROR(_xlfn.XLOOKUP(E1895,MapeoCargos!$A:$A,MapeoCargos!$B:$B,E1895),E1895)} -> CONDUCTOR/ASIST. DE GERENCIA | G1895: 44348
A1896: 71992701 | B1896: ABASTECEDORA ALIMENTICIA S.A.C. | C1896: ABASTECEDORA ALIMENTICIA | D1896: CRISTOBAL AYALA, ALVARO | E1896: PRODUCCION DE CREMAS | F1896: {=IFERROR(_xlfn.XLOOKUP(E1896,MapeoCargos!$A:$A,MapeoCargos!$B:$B,E1896),E1896)} -> PRODUCCION DE CREMAS | G1896: 44475
A1897: 48423886 | B1897: ABASTECEDORA ALIMENTICIA S.A.C. | C1897: ABASTECEDORA ALIMENTICIA | D1897: KONG CHIN, CARLOS ALFREDO | E1897: GERENTE GENERAL | F1897: {=IFERROR(_xlfn.XLOOKUP(E1897,MapeoCargos!$A:$A,MapeoCargos!$B:$B,E1897),E1897)} -> GERENTE GENERAL | G1897: 44491
A1898: 79300272 | B1898: ABASTECEDORA ALIMENTICIA S.A.C. | C1898: ABASTECEDORA ALIMENTICIA | D1898: VILLADEZA MOLINA, CRISTIAN FABIAN | E1898: AYUDANTE DE REPARTO | F1898: {=IFERROR(_xlfn.XLOOKUP(E1898,MapeoCargos!$A:$A,MapeoCargos!$B:$B,E1898),E1898)} -> AYUDANTE DE REPARTO | G1898: 44575
A1899: 60255936 | B1899: ABASTECEDORA ALIMENTICIA S.A.C. | C1899: ABASTECEDORA ALIMENTICIA | D1899: SANTIAGO AYALA, YERSON | E1899: PRODUCCION DE VERDURAS | F1899: {=IFERROR(_xlfn.XLOOKUP(E1899,MapeoCargos!$A:$A,MapeoCargos!$B:$B,E1899),E1899)} -> PRODUCCION DE VERDURAS | G1899: 44691
A1900: 71246944 | B1900: ABASTECEDORA ALIMENTICIA S.A.C. | C1900: ABASTECEDORA ALIMENTICIA | D1900: VASQUEZ SHAPIAMA, DANY | E1900: AYUDANTE DE REPARTO | F1900: {=IFERROR(_xlfn.XLOOKUP(E1900,MapeoCargos!$A:$A,MapeoCargos!$B:$B,E1900),E1900)} -> AYUDANTE DE REPARTO | G1900: 44705
A1901: 9302391 | B1901: ABASTECEDORA ALIMENTICIA S.A.C. | C1901: ABASTECEDORA ALIMENTICIA | D1901: LEE CHUY, JHONNY GUILLERMO | E1901: GERENTE DE IMPORTACIONES | F1901: {=IFERROR(_xlfn.XLOOKUP(E1901,MapeoCargos!$A:$A,MapeoCargos!$B:$B,E1901),E1901)} -> GERENTE DE IMPORTACIONES | G1901: 44805
A1902: 72701512 | B1902: ABASTECEDORA ALIMENTICIA S.A.C. | C1902: ABASTECEDORA ALIMENTICIA | D1902: SALHUANA MENDOZA, KAROL ROMINA | E1902: ASISTENTE DE LOGISTICA | F1902: {=IFERROR(_xlfn.XLOOKUP(E1902,MapeoCargos!$A:$A,MapeoCargos!$B:$B,E1902),E1902)} -> ASISTENTE DE LOGISTICA | G1902: 44959
A1903: 74148761 | B1903: ABASTECEDORA ALIMENTICIA S.A.C. | C1903: ABASTECEDORA ALIMENTICIA | D1903: VERTIZ GARCIA, MAYUMI ALEJANDRA | E1903: JEFE DE PRODUCCION Y CALIDAD | F1903: {=IFERROR(_xlfn.XLOOKUP(E1903,MapeoCargos!$A:$A,MapeoCargos!$B:$B,E1903),E1903)} -> JEFE DE PRODUCCION Y CALIDAD | G1903: 45064
A1904: 47033097 | B1904: ABASTECEDORA ALIMENTICIA S.A.C. | C1904: ABASTECEDORA ALIMENTICIA | D1904: LLANOS SILVA, LENER | E1904: CONDUCTOR | F1904: {=IFERROR(_xlfn.XLOOKUP(E1904,MapeoCargos!$A:$A,MapeoCargos!$B:$B,E1904),E1904)} -> CONDUCTOR | G1904: 45139
A1905: 71415598 | B1905: ABASTECEDORA ALIMENTICIA S.A.C. | C1905: ABASTECEDORA ALIMENTICIA | D1905: CRISOSTOMO DIAZ, ANTONIO | E1905: ASISTENTE DE AUDITORIA | F1905: {=IFERROR(_xlfn.XLOOKUP(E1905,MapeoCargos!$A:$A,MapeoCargos!$B:$B,E1905),E1905)} -> ASISTENTE DE AUDITORIA | G1905: 45139
...

Sheet Precios
A1: GRUPO | B1: CARGO ESTANDAR | C1: MATERIAL | D1: PRECIO (S,M,L) | E1: PRECIO (XL) | F1: PRECIO (XXL) | G1: CLAVE
A2: LIMA E ICA PROVINCIA | B2: MOTORIZADO | C2: POLO PIQUÉ PLOMO, MANGA LARGA MOTORIZADO | D2: =34/2 -> 17 | E2: =34/2 -> 17 | F2: =34/2 -> 17 | G2: =IF( OR(A2="",B2="",C2=""), "", CLEAN(TRIM(A2)) & "|" & CLEAN(TRIM(B2)) & "|" & CLEAN(TRIM(C2)) ) -> LIMA E ICA PROVINCIA|MOTORIZADO|POLO PIQUÉ PLOMO, MANGA LARGA MOTORIZADO
A3: LIMA E ICA PROVINCIA | B3: MOTORIZADO | C3: GORRO NEGRO MOTORIZADO | D3: =10/2 -> 5 | E3: =10/2 -> 5 | F3: =10/2 -> 5 | G3: =IF( OR(A3="",B3="",C3=""), "", CLEAN(TRIM(A3)) & "|" & CLEAN(TRIM(B3)) & "|" & CLEAN(TRIM(C3)) ) -> LIMA E ICA PROVINCIA|MOTORIZADO|GORRO NEGRO MOTORIZADO
A4: LIMA E ICA PROVINCIA | B4: MOTORIZADO | C4: CASACA NEGRA CON REFLECTIVOS MOTORIZADO | D4: 39 | E4: 39 | F4: 41 | G4: =IF( OR(A4="",B4="",C4=""), "", CLEAN(TRIM(A4)) & "|" & CLEAN(TRIM(B4)) & "|" & CLEAN(TRIM(C4)) ) -> LIMA E ICA PROVINCIA|MOTORIZADO|CASACA NEGRA CON REFLECTIVOS MOTORIZADO
A5: LIMA E ICA PROVINCIA | B5: PACKER | C5: POLO PIQUÉ PLOMO, MANGA LARGA PACKER | D5: =34/2 -> 17 | E5: =34/2 -> 17 | F5: =36/2 -> 18 | G5: =IF( OR(A5="",B5="",C5=""), "", CLEAN(TRIM(A5)) & "|" & CLEAN(TRIM(B5)) & "|" & CLEAN(TRIM(C5)) ) -> LIMA E ICA PROVINCIA|PACKER|POLO PIQUÉ PLOMO, MANGA LARGA PACKER
A6: LIMA E ICA PROVINCIA | B6: PACKER | C6: GORRO NEGRO PACKER | D6: =10/2 -> 5 | E6: =10/2 -> 5 | F6: =10/2 -> 5 | G6: =IF( OR(A6="",B6="",C6=""), "", CLEAN(TRIM(A6)) & "|" & CLEAN(TRIM(B6)) & "|" & CLEAN(TRIM(C6)) ) -> LIMA E ICA PROVINCIA|PACKER|GORRO NEGRO PACKER
A7: LIMA E ICA PROVINCIA | B7: PACKER | C7: CASACA NEGRA CON REFLECTIVOS PACKER | D7: 39 | E7: 39 | F7: 41 | G7: =IF( OR(A7="",B7="",C7=""), "", CLEAN(TRIM(A7)) & "|" & CLEAN(TRIM(B7)) & "|" & CLEAN(TRIM(C7)) ) -> LIMA E ICA PROVINCIA|PACKER|CASACA NEGRA CON REFLECTIVOS PACKER
A8: LIMA E ICA PROVINCIA | B8: STAFF ADMINISTRATIVO | C8: CAMISA OXFORD CELESTE | D8: =36/2 -> 18 | E8: =36/2 -> 18 | F8: =38/2 -> 19 | G8: =IF( OR(A8="",B8="",C8=""), "", CLEAN(TRIM(A8)) & "|" & CLEAN(TRIM(B8)) & "|" & CLEAN(TRIM(C8)) ) -> LIMA E ICA PROVINCIA|STAFF ADMINISTRATIVO|CAMISA OXFORD CELESTE
A9: LIMA E ICA PROVINCIA | B9: STAFF ADMINISTRATIVO | C9: SACO NEGRO ADM HOMBRE | D9: 60 | E9: 60 | F9: 62.5 | G9: =IF( OR(A9="",B9="",C9=""), "", CLEAN(TRIM(A9)) & "|" & CLEAN(TRIM(B9)) & "|" & CLEAN(TRIM(C9)) ) -> LIMA E ICA PROVINCIA|STAFF ADMINISTRATIVO|SACO NEGRO ADM HOMBRE
A10: LIMA E ICA PROVINCIA | B10: STAFF ADMINISTRATIVO | C10: POLO PIQUÉ PIZARRA RX, MANGA CORTA ADM | D10: =27/2 -> 13.5 | E10: =27/2 -> 13.5 | F10: =30/2 -> 15 | G10: =IF( OR(A10="",B10="",C10=""), "", CLEAN(TRIM(A10)) & "|" & CLEAN(TRIM(B10)) & "|" & CLEAN(TRIM(C10)) ) -> LIMA E ICA PROVINCIA|STAFF ADMINISTRATIVO|POLO PIQUÉ PIZARRA RX, MANGA CORTA ADM
A11: LIMA E ICA PROVINCIA | B11: STAFF ADMINISTRATIVO | C11: BLUSA OXFORD CELESTE | D11: =36/2 -> 18 | E11: =36/2 -> 18 | F11: =38/2 -> 19 | G11: =IF( OR(A11="",B11="",C11=""), "", CLEAN(TRIM(A11)) & "|" & CLEAN(TRIM(B11)) & "|" & CLEAN(TRIM(C11)) ) -> LIMA E ICA PROVINCIA|STAFF ADMINISTRATIVO|BLUSA OXFORD CELESTE
A12: LIMA E ICA PROVINCIA | B12: STAFF ADMINISTRATIVO | C12: SACO NEGRO ADM MUJER | D12: 35 | E12: 35 | F12: 37.5 | G12: =IF( OR(A12="",B12="",C12=""), "", CLEAN(TRIM(A12)) & "|" & CLEAN(TRIM(B12)) & "|" & CLEAN(TRIM(C12)) ) -> LIMA E ICA PROVINCIA|STAFF ADMINISTRATIVO|SACO NEGRO ADM MUJER
A13: LIMA E ICA PROVINCIA | B13: STAFF ADMINISTRATIVO | C13: POLO PIQUÉ PIZARRA RX, MANGA CORTA ADMI | D13: 15 | E13: 15 | F13: 16 | G13: =IF( OR(A13="",B13="",C13=""), "", CLEAN(TRIM(A13)) & "|" & CLEAN(TRIM(B13)) & "|" & CLEAN(TRIM(C13)) ) -> LIMA E ICA PROVINCIA|STAFF ADMINISTRATIVO|POLO PIQUÉ PIZARRA RX, MANGA CORTA ADMI
A14: LIMA E ICA PROVINCIA | B14: STAFF ADMINISTRATIVO | C14: CASACA ADM | D14: 39 | E14: 39 | F14: 41 | G14: =IF( OR(A14="",B14="",C14=""), "", CLEAN(TRIM(A14)) & "|" & CLEAN(TRIM(B14)) & "|" & CLEAN(TRIM(C14)) ) -> LIMA E ICA PROVINCIA|STAFF ADMINISTRATIVO|CASACA ADM
A15: LIMA E ICA PROVINCIA | B15: STAFF ADMINISTRATIVO | C15: PANTALÓN SAL Y PIMIENTA | D15: =22/2 -> 11 | E15: =22/2 -> 11 | F15: =23/2 -> 11.5 | G15: =IF( OR(A15="",B15="",C15=""), "", CLEAN(TRIM(A15)) & "|" & CLEAN(TRIM(B15)) & "|" & CLEAN(TRIM(C15)) ) -> LIMA E ICA PROVINCIA|STAFF ADMINISTRATIVO|PANTALÓN SAL Y PIMIENTA
A16: LIMA E ICA PROVINCIA | B16: STAFF ADMINISTRATIVO | C16: PECHERA GRIS EN DRILL | D16: =13/2 -> 6.5 | E16: =13/2 -> 6.5 | F16: =13/2 -> 6.5 | G16: =IF( OR(A16="",B16="",C16=""), "", CLEAN(TRIM(A16)) & "|" & CLEAN(TRIM(B16)) & "|" & CLEAN(TRIM(C16)) ) -> LIMA E ICA PROVINCIA|STAFF ADMINISTRATIVO|PECHERA GRIS EN DRILL
A17: LIMA E ICA PROVINCIA | B17: STAFF ADMINISTRATIVO | C17: GARIBALDI GRIS | D17: =9/2 -> 4.5 | E17: =9/2 -> 4.5 | F17: =9/2 -> 4.5 | G17: =IF( OR(A17="",B17="",C17=""), "", CLEAN(TRIM(A17)) & "|" & CLEAN(TRIM(B17)) & "|" & CLEAN(TRIM(C17)) ) -> LIMA E ICA PROVINCIA|STAFF ADMINISTRATIVO|GARIBALDI GRIS
A18: LIMA E ICA PROVINCIA | B18: STAFF ADMINISTRATIVO | C18: CHAQUETA DRILL BLANCO | D18: =32.5/2 -> 16.25 | E18: =32.5/2 -> 16.25 | F18: =34.5/2 -> 17.25 | G18: =IF( OR(A18="",B18="",C18=""), "", CLEAN(TRIM(A18)) & "|" & CLEAN(TRIM(B18)) & "|" & CLEAN(TRIM(C18)) ) -> LIMA E ICA PROVINCIA|STAFF ADMINISTRATIVO|CHAQUETA DRILL BLANCO
A19: LIMA E ICA PROVINCIA | B19: STAFF ADMINISTRATIVO | C19: POLO 30/1 GRIS | D19: =15/2 -> 7.5 | E19: =15/2 -> 7.5 | F19: =17/2 -> 8.5 | G19: =IF( OR(A19="",B19="",C19=""), "", CLEAN(TRIM(A19)) & "|" & CLEAN(TRIM(B19)) & "|" & CLEAN(TRIM(C19)) ) -> LIMA E ICA PROVINCIA|STAFF ADMINISTRATIVO|POLO 30/1 GRIS
A20: LIMA E ICA PROVINCIA | B20: STAFF ADMINISTRATIVO | C20: GORRO NEGRO ADM | D20: =10/2 -> 5 | E20: =10/2 -> 5 | F20: =10/2 -> 5 | G20: =IF( OR(A20="",B20="",C20=""), "", CLEAN(TRIM(A20)) & "|" & CLEAN(TRIM(B20)) & "|" & CLEAN(TRIM(C20)) ) -> LIMA E ICA PROVINCIA|STAFF ADMINISTRATIVO|GORRO NEGRO ADM
A21: LIMA E ICA PROVINCIA | B21: CAJA | C21: CAMISA A RALLAS AZUL | D21: =36/2 -> 18 | E21: =36/2 -> 18 | F21: =38/2 -> 19 | G21: =IF( OR(A21="",B21="",C21=""), "", CLEAN(TRIM(A21)) & "|" & CLEAN(TRIM(B21)) & "|" & CLEAN(TRIM(C21)) ) -> LIMA E ICA PROVINCIA|CAJA|CAMISA A RALLAS AZUL
A22: LIMA E ICA PROVINCIA | B22: CAJA | C22: PANTALÓN AZUL NOCHE | D22: =40/2 -> 20 | E22: =40/2 -> 20 | F22: =42/2 -> 21 | G22: =IF( OR(A22="",B22="",C22=""), "", CLEAN(TRIM(A22)) & "|" & CLEAN(TRIM(B22)) & "|" & CLEAN(TRIM(C22)) ) -> LIMA E ICA PROVINCIA|CAJA|PANTALÓN AZUL NOCHE
A23: LIMA E ICA PROVINCIA | B23: CAJA | C23: CHALECO AZUL NOCHE | D23: =35/2 -> 17.5 | E23: =35/2 -> 17.5 | F23: =37/2 -> 18.5 | G23: =IF( OR(A23="",B23="",C23=""), "", CLEAN(TRIM(A23)) & "|" & CLEAN(TRIM(B23)) & "|" & CLEAN(TRIM(C23)) ) -> LIMA E ICA PROVINCIA|CAJA|CHALECO AZUL NOCHE
A24: LIMA E ICA PROVINCIA | B24: CAJA | C24: SACO NEGRO CAJA HOMBRE | D24: 60 | E24: 60 | F24: 62.5 | G24: =IF( OR(A24="",B24="",C24=""), "", CLEAN(TRIM(A24)) & "|" & CLEAN(TRIM(B24)) & "|" & CLEAN(TRIM(C24)) ) -> LIMA E ICA PROVINCIA|CAJA|SACO NEGRO CAJA HOMBRE
A25: LIMA E ICA PROVINCIA | B25: CAJA | C25: BLUSA A RALLAS AZUL | D25: =36/2 -> 18 | E25: =36/2 -> 18 | F25: =38/2 -> 19 | G25: =IF( OR(A25="",B25="",C25=""), "", CLEAN(TRIM(A25)) & "|" & CLEAN(TRIM(B25)) & "|" & CLEAN(TRIM(C25)) ) -> LIMA E ICA PROVINCIA|CAJA|BLUSA A RALLAS AZUL
A26: LIMA E ICA PROVINCIA | B26: CAJA | C26: PANTALÓN AZUL NOCHE | D26: =40/2 -> 20 | E26: =40/2 -> 20 | F26: =42/2 -> 21 | G26: =IF( OR(A26="",B26="",C26=""), "", CLEAN(TRIM(A26)) & "|" & CLEAN(TRIM(B26)) & "|" & CLEAN(TRIM(C26)) ) -> LIMA E ICA PROVINCIA|CAJA|PANTALÓN AZUL NOCHE
A27: LIMA E ICA PROVINCIA | B27: CAJA | C27: CHALECO AZUL NOCHE | D27: =35/2 -> 17.5 | E27: =35/2 -> 17.5 | F27: =37/2 -> 18.5 | G27: =IF( OR(A27="",B27="",C27=""), "", CLEAN(TRIM(A27)) & "|" & CLEAN(TRIM(B27)) & "|" & CLEAN(TRIM(C27)) ) -> LIMA E ICA PROVINCIA|CAJA|CHALECO AZUL NOCHE
A28: LIMA E ICA PROVINCIA | B28: CAJA | C28: SACO NEGRO CAJA MUJER | D28: 35 | E28: 35 | F28: 37.5 | G28: =IF( OR(A28="",B28="",C28=""), "", CLEAN(TRIM(A28)) & "|" & CLEAN(TRIM(B28)) & "|" & CLEAN(TRIM(C28)) ) -> LIMA E ICA PROVINCIA|CAJA|SACO NEGRO CAJA MUJER
A29: LIMA E ICA PROVINCIA | B29: CAJA | C29: CASACA CAJA | D29: 39 | E29: 39 | F29: 41 | G29: =IF( OR(A29="",B29="",C29=""), "", CLEAN(TRIM(A29)) & "|" & CLEAN(TRIM(B29)) & "|" & CLEAN(TRIM(C29)) ) -> LIMA E ICA PROVINCIA|CAJA|CASACA CAJA
A30: LIMA E ICA PROVINCIA | B30: MOZO | C30: CAMISA BLANCA (MANGA LARGA) | D30: =37/2 -> 18.5 | E30: =37/2 -> 18.5 | F30: =39/2 -> 19.5 | G30: =IF( OR(A30="",B30="",C30=""), "", CLEAN(TRIM(A30)) & "|" & CLEAN(TRIM(B30)) & "|" & CLEAN(TRIM(C30)) ) -> LIMA E ICA PROVINCIA|MOZO|CAMISA BLANCA (MANGA LARGA)
A31: LIMA E ICA PROVINCIA | B31: MOZO | C31: MANDILON DRILL NEGRO | D31: =14/2 -> 7 | E31: =14/2 -> 7 | F31: =14/2 -> 7 | G31: =IF( OR(A31="",B31="",C31=""), "", CLEAN(TRIM(A31)) & "|" & CLEAN(TRIM(B31)) & "|" & CLEAN(TRIM(C31)) ) -> LIMA E ICA PROVINCIA|MOZO|MANDILON DRILL NEGRO
A32: LIMA E ICA PROVINCIA | B32: MOZO | C32: ANDARIN GRANATE | D32: =3.5/2 -> 1.75 | E32: =3.5/2 -> 1.75 | F32: =3.5/2 -> 1.75 | G32: =IF( OR(A32="",B32="",C32=""), "", CLEAN(TRIM(A32)) & "|" & CLEAN(TRIM(B32)) & "|" & CLEAN(TRIM(C32)) ) -> LIMA E ICA PROVINCIA|MOZO|ANDARIN GRANATE
A33: LIMA E ICA PROVINCIA | B33: MOZO | C33: POLO 31/1 GRIS | D33: 7.5 | E33: 7.5 | F33: 8.5 | G33: =IF( OR(A33="",B33="",C33=""), "", CLEAN(TRIM(A33)) & "|" & CLEAN(TRIM(B33)) & "|" & CLEAN(TRIM(C33)) ) -> LIMA E ICA PROVINCIA|MOZO|POLO 31/1 GRIS
A34: LIMA E ICA PROVINCIA | B34: MOZO | C34: CAMISA OXFORD CONCHE VINO | D34: =43/2 -> 21.5 | E34: =43/2 -> 21.5 | F34: =46/2 -> 23 | G34: =IF( OR(A34="",B34="",C34=""), "", CLEAN(TRIM(A34)) & "|" & CLEAN(TRIM(B34)) & "|" & CLEAN(TRIM(C34)) ) -> LIMA E ICA PROVINCIA|MOZO|CAMISA OXFORD CONCHE VINO
A35: LIMA E ICA PROVINCIA | B35: MOZO | C35: PECHERA NEGRA ENTRENADOR DE SERVICIO | D35: 12 | E35: 12 | F35: 12 | G35: =IF( OR(A35="",B35="",C35=""), "", CLEAN(TRIM(A35)) & "|" & CLEAN(TRIM(B35)) & "|" & CLEAN(TRIM(C35)) ) -> LIMA E ICA PROVINCIA|MOZO|PECHERA NEGRA ENTRENADOR DE SERVICIO
A36: LIMA E ICA PROVINCIA | B36: AZAFATA | C36: BLUSA BLANCA (MANGA LARGA) | D36: =37/2 -> 18.5 | E36: =37/2 -> 18.5 | F36: =39/2 -> 19.5 | G36: =IF( OR(A36="",B36="",C36=""), "", CLEAN(TRIM(A36)) & "|" & CLEAN(TRIM(B36)) & "|" & CLEAN(TRIM(C36)) ) -> LIMA E ICA PROVINCIA|AZAFATA|BLUSA BLANCA (MANGA LARGA)
A37: LIMA E ICA PROVINCIA | B37: AZAFATA | C37: MANDILON DRILL NEGRO | D37: =14/2 -> 7 | E37: =14/2 -> 7 | F37: =14/2 -> 7 | G37: =IF( OR(A37="",B37="",C37=""), "", CLEAN(TRIM(A37)) & "|" & CLEAN(TRIM(B37)) & "|" & CLEAN(TRIM(C37)) ) -> LIMA E ICA PROVINCIA|AZAFATA|MANDILON DRILL NEGRO
A38: LIMA E ICA PROVINCIA | B38: AZAFATA | C38: ANDARIN GRANATE | D38: =3.5/2 -> 1.75 | E38: =3.5/2 -> 1.75 | F38: =3.5/2 -> 1.75 | G38: =IF( OR(A38="",B38="",C38=""), "", CLEAN(TRIM(A38)) & "|" & CLEAN(TRIM(B38)) & "|" & CLEAN(TRIM(C38)) ) -> LIMA E ICA PROVINCIA|AZAFATA|ANDARIN GRANATE
A39: LIMA E ICA PROVINCIA | B39: SEGURIDAD | C39: CAMISA CHARCOL MANGA LARGA | D39: =36/2 -> 18 | E39: =36/2 -> 18 | F39: =38/2 -> 19 | G39: =IF( OR(A39="",B39="",C39=""), "", CLEAN(TRIM(A39)) & "|" & CLEAN(TRIM(B39)) & "|" & CLEAN(TRIM(C39)) ) -> LIMA E ICA PROVINCIA|SEGURIDAD|CAMISA CHARCOL MANGA LARGA
A40: LIMA E ICA PROVINCIA | B40: SEGURIDAD | C40: GORRA NEGRA SEGURIDAD | D40: =10/2 -> 5 | E40: =10/2 -> 5 | F40: =10/2 -> 5 | G40: =IF( OR(A40="",B40="",C40=""), "", CLEAN(TRIM(A40)) & "|" & CLEAN(TRIM(B40)) & "|" & CLEAN(TRIM(C40)) ) -> LIMA E ICA PROVINCIA|SEGURIDAD|GORRA NEGRA SEGURIDAD
A41: LIMA E ICA PROVINCIA | B41: SEGURIDAD | C41: CASACA NEGRA SEGURIDAD | D41: 39 | E41: 39 | F41: 39 | G41: =IF( OR(A41="",B41="",C41=""), "", CLEAN(TRIM(A41)) & "|" & CLEAN(TRIM(B41)) & "|" & CLEAN(TRIM(C41)) ) -> LIMA E ICA PROVINCIA|SEGURIDAD|CASACA NEGRA SEGURIDAD
A42: LIMA E ICA PROVINCIA | B42: ANFITRIONAJE | C42: CAMISA COLOR NEGRO MANGA LARGA | D42: =36/2 -> 18 | E42: =36/2 -> 18 | F42: =38/2 -> 19 | G42: =IF( OR(A42="",B42="",C42=""), "", CLEAN(TRIM(A42)) & "|" & CLEAN(TRIM(B42)) & "|" & CLEAN(TRIM(C42)) ) -> LIMA E ICA PROVINCIA|ANFITRIONAJE|CAMISA COLOR NEGRO MANGA LARGA
A43: LIMA E ICA PROVINCIA | B43: ANFITRIONAJE | C43: SACO NEGRO ANFITRIONAJE HOMBRE | D43: 60 | E43: 60 | F43: 62.5 | G43: =IF( OR(A43="",B43="",C43=""), "", CLEAN(TRIM(A43)) & "|" & CLEAN(TRIM(B43)) & "|" & CLEAN(TRIM(C43)) ) -> LIMA E ICA PROVINCIA|ANFITRIONAJE|SACO NEGRO ANFITRIONAJE HOMBRE
A44: LIMA E ICA PROVINCIA | B44: ANFITRIONAJE | C44: BLUSA COLOR NEGRO MANGA LARGA | D44: =36/2 -> 18 | E44: =36/2 -> 18 | F44: =38/2 -> 19 | G44: =IF( OR(A44="",B44="",C44=""), "", CLEAN(TRIM(A44)) & "|" & CLEAN(TRIM(B44)) & "|" & CLEAN(TRIM(C44)) ) -> LIMA E ICA PROVINCIA|ANFITRIONAJE|BLUSA COLOR NEGRO MANGA LARGA
A45: LIMA E ICA PROVINCIA | B45: ANFITRIONAJE | C45: SACO NEGRO ANFITRIONAJE MUJER | D45: 35 | E45: 35 | F45: 37.5 | G45: =IF( OR(A45="",B45="",C45=""), "", CLEAN(TRIM(A45)) & "|" & CLEAN(TRIM(B45)) & "|" & CLEAN(TRIM(C45)) ) -> LIMA E ICA PROVINCIA|ANFITRIONAJE|SACO NEGRO ANFITRIONAJE MUJER
A46: LIMA E ICA PROVINCIA | B46: LIMPIEZA / MANTENIMIENTO | C46: PANTALÓN CARGO AZUL NOCHE | D46: =25/2 -> 12.5 | E46: =25/2 -> 12.5 | F46: =27/2 -> 13.5 | G46: =IF( OR(A46="",B46="",C46=""), "", CLEAN(TRIM(A46)) & "|" & CLEAN(TRIM(B46)) & "|" & CLEAN(TRIM(C46)) ) -> LIMA E ICA PROVINCIA|LIMPIEZA / MANTENIMIENTO|PANTALÓN CARGO AZUL NOCHE
A47: LIMA E ICA PROVINCIA | B47: LIMPIEZA / MANTENIMIENTO | C47: CHAQUETA AZUL NOCHE MANGA CORTA | D47: =28/2 -> 14 | E47: =28/2 -> 14 | F47: =30/2 -> 15 | G47: =IF( OR(A47="",B47="",C47=""), "", CLEAN(TRIM(A47)) & "|" & CLEAN(TRIM(B47)) & "|" & CLEAN(TRIM(C47)) ) -> LIMA E ICA PROVINCIA|LIMPIEZA / MANTENIMIENTO|CHAQUETA AZUL NOCHE MANGA CORTA
A48: LIMA E ICA PROVINCIA | B48: LIMPIEZA / MANTENIMIENTO | C48: POLO 30/1 GRIS | D48: =15/2 -> 7.5 | E48: =15/2 -> 7.5 | F48: =17/2 -> 8.5 | G48: =IF( OR(A48="",B48="",C48=""), "", CLEAN(TRIM(A48)) & "|" & CLEAN(TRIM(B48)) & "|" & CLEAN(TRIM(C48)) ) -> LIMA E ICA PROVINCIA|LIMPIEZA / MANTENIMIENTO|POLO 30/1 GRIS
A49: LIMA E ICA PROVINCIA | B49: BAR | C49: CAMISA NEGRA MANGA CORTA | D49: =33/2 -> 16.5 | E49: =33/2 -> 16.5 | F49: =35/2 -> 17.5 | G49: =IF( OR(A49="",B49="",C49=""), "", CLEAN(TRIM(A49)) & "|" & CLEAN(TRIM(B49)) & "|" & CLEAN(TRIM(C49)) ) -> LIMA E ICA PROVINCIA|BAR|CAMISA NEGRA MANGA CORTA
A50: LIMA E ICA PROVINCIA | B50: BAR | C50: PECHERA NEGRA CUERINA | D50: =39/2 -> 19.5 | E50: =39/2 -> 19.5 | F50: =39/2 -> 19.5 | G50: =IF( OR(A50="",B50="",C50=""), "", CLEAN(TRIM(A50)) & "|" & CLEAN(TRIM(B50)) & "|" & CLEAN(TRIM(C50)) ) -> LIMA E ICA PROVINCIA|BAR|PECHERA NEGRA CUERINA
A51: LIMA E ICA PROVINCIA | B51: BAR | C51: POLO 30/1 GRIS | D51: =15/2 -> 7.5 | E51: =15/2 -> 7.5 | F51: =17/2 -> 8.5 | G51: =IF( OR(A51="",B51="",C51=""), "", CLEAN(TRIM(A51)) & "|" & CLEAN(TRIM(B51)) & "|" & CLEAN(TRIM(C51)) ) -> LIMA E ICA PROVINCIA|BAR|POLO 30/1 GRIS
A52: LIMA E ICA PROVINCIA | B52: PRODUCCIÓN / COCINA | C52: PANTALÓN SAL Y PIMIENTA | D52: =22/2 -> 11 | E52: =22/2 -> 11 | F52: =23/2 -> 11.5 | G52: =IF( OR(A52="",B52="",C52=""), "", CLEAN(TRIM(A52)) & "|" & CLEAN(TRIM(B52)) & "|" & CLEAN(TRIM(C52)) ) -> LIMA E ICA PROVINCIA|PRODUCCIÓN / COCINA|PANTALÓN SAL Y PIMIENTA
A53: LIMA E ICA PROVINCIA | B53: PRODUCCIÓN / COCINA | C53: PECHERA GRIS EN DRILL | D53: =13/2 -> 6.5 | E53: =13/2 -> 6.5 | F53: =13/2 -> 6.5 | G53: =IF( OR(A53="",B53="",C53=""), "", CLEAN(TRIM(A53)) & "|" & CLEAN(TRIM(B53)) & "|" & CLEAN(TRIM(C53)) ) -> LIMA E ICA PROVINCIA|PRODUCCIÓN / COCINA|PECHERA GRIS EN DRILL
A54: LIMA E ICA PROVINCIA | B54: PRODUCCIÓN / COCINA | C54: GARIBALDI GRIS | D54: =9/2 -> 4.5 | E54: =9/2 -> 4.5 | F54: =9/2 -> 4.5 | G54: =IF( OR(A54="",B54="",C54=""), "", CLEAN(TRIM(A54)) & "|" & CLEAN(TRIM(B54)) & "|" & CLEAN(TRIM(C54)) ) -> LIMA E ICA PROVINCIA|PRODUCCIÓN / COCINA|GARIBALDI GRIS
A55: LIMA E ICA PROVINCIA | B55: PRODUCCIÓN / COCINA | C55: CHAQUETA DRILL BLANCO | D55: =32.5/2 -> 16.25 | E55: =32.5/2 -> 16.25 | F55: =34.5/2 -> 17.25 | G55: =IF( OR(A55="",B55="",C55=""), "", CLEAN(TRIM(A55)) & "|" & CLEAN(TRIM(B55)) & "|" & CLEAN(TRIM(C55)) ) -> LIMA E ICA PROVINCIA|PRODUCCIÓN / COCINA|CHAQUETA DRILL BLANCO
A56: LIMA E ICA PROVINCIA | B56: PRODUCCIÓN / COCINA | C56: POLO 30/1 GRIS | D56: =15/2 -> 7.5 | E56: =15/2 -> 7.5 | F56: =17/2 -> 8.5 | G56: =IF( OR(A56="",B56="",C56=""), "", CLEAN(TRIM(A56)) & "|" & CLEAN(TRIM(B56)) & "|" & CLEAN(TRIM(C56)) ) -> LIMA E ICA PROVINCIA|PRODUCCIÓN / COCINA|POLO 30/1 GRIS
A57: LIMA E ICA PROVINCIA | B57: AUDITORIA | C57: POLO PIQUÉ NEGRO RX AUDITORIA | D57: =27/2 -> 13.5 | E57: =27/2 -> 13.5 | F57: =27/2 -> 13.5 | G57: =IF( OR(A57="",B57="",C57=""), "", CLEAN(TRIM(A57)) & "|" & CLEAN(TRIM(B57)) & "|" & CLEAN(TRIM(C57)) ) -> LIMA E ICA PROVINCIA|AUDITORIA|POLO PIQUÉ NEGRO RX AUDITORIA
A58: LIMA E ICA PROVINCIA | B58: AUDITORIA | C58: CASACA GRIS | D58: 37 | E58: 37 | F58: 37 | G58: =IF( OR(A58="",B58="",C58=""), "", CLEAN(TRIM(A58)) & "|" & CLEAN(TRIM(B58)) & "|" & CLEAN(TRIM(C58)) ) -> LIMA E ICA PROVINCIA|AUDITORIA|CASACA GRIS
A59: TARAPOTO | B59: MOZO | C59: CAMISA BLANCA (MANGA CORTA) | D59: =34/2 -> 17 | E59: =34/2 -> 17 | F59: =36/2 -> 18 | G59: =IF( OR(A59="",B59="",C59=""), "", CLEAN(TRIM(A59)) & "|" & CLEAN(TRIM(B59)) & "|" & CLEAN(TRIM(C59)) ) -> TARAPOTO|MOZO|CAMISA BLANCA (MANGA CORTA)
A60: TARAPOTO | B60: MOZO | C60: MANDILON DRILL NEGRO | D60: =14/2 -> 7 | E60: =14/2 -> 7 | F60: =14/2 -> 7 | G60: =IF( OR(A60="",B60="",C60=""), "", CLEAN(TRIM(A60)) & "|" & CLEAN(TRIM(B60)) & "|" & CLEAN(TRIM(C60)) ) -> TARAPOTO|MOZO|MANDILON DRILL NEGRO
A61: TARAPOTO | B61: MOZO | C61: ANDARIN GRANATE | D61: =3.5/2 -> 1.75 | E61: =3.5/2 -> 1.75 | F61: =3.5/2 -> 1.75 | G61: =IF( OR(A61="",B61="",C61=""), "", CLEAN(TRIM(A61)) & "|" & CLEAN(TRIM(B61)) & "|" & CLEAN(TRIM(C61)) ) -> TARAPOTO|MOZO|ANDARIN GRANATE
A62: TARAPOTO | B62: AZAFATA | C62: BLUSA BLANCA (MANGA CORTA) | D62: =34/2 -> 17 | E62: =34/2 -> 17 | F62: =36/2 -> 18 | G62: =IF( OR(A62="",B62="",C62=""), "", CLEAN(TRIM(A62)) & "|" & CLEAN(TRIM(B62)) & "|" & CLEAN(TRIM(C62)) ) -> TARAPOTO|AZAFATA|BLUSA BLANCA (MANGA CORTA)
A63: TARAPOTO | B63: AZAFATA | C63: MANDILON DRILL NEGRO | D63: =14/2 -> 7 | E63: =14/2 -> 7 | F63: =14/2 -> 7 | G63: =IF( OR(A63="",B63="",C63=""), "", CLEAN(TRIM(A63)) & "|" & CLEAN(TRIM(B63)) & "|" & CLEAN(TRIM(C63)) ) -> TARAPOTO|AZAFATA|MANDILON DRILL NEGRO
A64: TARAPOTO | B64: AZAFATA | C64: ANDARIN GRANATE | D64: =3.5/2 -> 1.75 | E64: =3.5/2 -> 1.75 | F64: =3.5/2 -> 1.75 | G64: =IF( OR(A64="",B64="",C64=""), "", CLEAN(TRIM(A64)) & "|" & CLEAN(TRIM(B64)) & "|" & CLEAN(TRIM(C64)) ) -> TARAPOTO|AZAFATA|ANDARIN GRANATE
A65: TARAPOTO | B65: PACKER | C65: POLO PIQUÉ CONCHE VINO, MANGA CORTA PACKER | D65: =27/2 -> 13.5 | E65: =27/2 -> 13.5 | F65: =30/2 -> 15 | G65: =IF( OR(A65="",B65="",C65=""), "", CLEAN(TRIM(A65)) & "|" & CLEAN(TRIM(B65)) & "|" & CLEAN(TRIM(C65)) ) -> TARAPOTO|PACKER|POLO PIQUÉ CONCHE VINO, MANGA CORTA PACKER
A66: TARAPOTO | B66: PACKER | C66: GORRO JOCKEY CONCHE VINO PACKER | D66: =10/2 -> 5 | E66: =10/2 -> 5 | F66: =10/2 -> 5 | G66: =IF( OR(A66="",B66="",C66=""), "", CLEAN(TRIM(A66)) & "|" & CLEAN(TRIM(B66)) & "|" & CLEAN(TRIM(C66)) ) -> TARAPOTO|PACKER|GORRO JOCKEY CONCHE VINO PACKER
A67: TARAPOTO | B67: MOTORIZADO | C67: POLO PIQUÉ CONCHE VINO, MANGA CORTA MOTORIZADO | D67: =27/2 -> 13.5 | E67: =27/2 -> 13.5 | F67: =30/2 -> 15 | G67: =IF( OR(A67="",B67="",C67=""), "", CLEAN(TRIM(A67)) & "|" & CLEAN(TRIM(B67)) & "|" & CLEAN(TRIM(C67)) ) -> TARAPOTO|MOTORIZADO|POLO PIQUÉ CONCHE VINO, MANGA CORTA MOTORIZADO
A68: TARAPOTO | B68: MOTORIZADO | C68: GORRO JOCKEY CONCHE VINO MOTORIZADO | D68: =10/2 -> 5 | E68: =10/2 -> 5 | F68: =10/2 -> 5 | G68: =IF( OR(A68="",B68="",C68=""), "", CLEAN(TRIM(A68)) & "|" & CLEAN(TRIM(B68)) & "|" & CLEAN(TRIM(C68)) ) -> TARAPOTO|MOTORIZADO|GORRO JOCKEY CONCHE VINO MOTORIZADO
A69: TARAPOTO | B69: MOTORIZADO | C69: CASACA NEGRA CON REFLECTIVOS MOTORIZADO | D69: 39 | E69: 39 | F69: 41 | G69: =IF( OR(A69="",B69="",C69=""), "", CLEAN(TRIM(A69)) & "|" & CLEAN(TRIM(B69)) & "|" & CLEAN(TRIM(C69)) ) -> TARAPOTO|MOTORIZADO|CASACA NEGRA CON REFLECTIVOS MOTORIZADO
A70: TARAPOTO | B70: STAFF ADMINISTRATIVO | C70: CAMISA OXFORD CELESTE | D70: =36/2 -> 18 | E70: =36/2 -> 18 | F70: =38/2 -> 19 | G70: =IF( OR(A70="",B70="",C70=""), "", CLEAN(TRIM(A70)) & "|" & CLEAN(TRIM(B70)) & "|" & CLEAN(TRIM(C70)) ) -> TARAPOTO|STAFF ADMINISTRATIVO|CAMISA OXFORD CELESTE
A71: TARAPOTO | B71: STAFF ADMINISTRATIVO | C71: SACO NEGRO ADM HOMBRE | D71: 60 | E71: 60 | F71: 62.5 | G71: =IF( OR(A71="",B71="",C71=""), "", CLEAN(TRIM(A71)) & "|" & CLEAN(TRIM(B71)) & "|" & CLEAN(TRIM(C71)) ) -> TARAPOTO|STAFF ADMINISTRATIVO|SACO NEGRO ADM HOMBRE
A72: TARAPOTO | B72: STAFF ADMINISTRATIVO | C72: POLO PIQUÉ PIZARRA RX, MANGA CORTA ADM | D72: =27/2 -> 13.5 | E72: =27/2 -> 13.5 | F72: =30/2 -> 15 | G72: =IF( OR(A72="",B72="",C72=""), "", CLEAN(TRIM(A72)) & "|" & CLEAN(TRIM(B72)) & "|" & CLEAN(TRIM(C72)) ) -> TARAPOTO|STAFF ADMINISTRATIVO|POLO PIQUÉ PIZARRA RX, MANGA CORTA ADM
A73: TARAPOTO | B73: STAFF ADMINISTRATIVO | C73: BLUSA OXFORD CELESTE | D73: =36/2 -> 18 | E73: =36/2 -> 18 | F73: =38/2 -> 19 | G73: =IF( OR(A73="",B73="",C73=""), "", CLEAN(TRIM(A73)) & "|" & CLEAN(TRIM(B73)) & "|" & CLEAN(TRIM(C73)) ) -> TARAPOTO|STAFF ADMINISTRATIVO|BLUSA OXFORD CELESTE
A74: TARAPOTO | B74: STAFF ADMINISTRATIVO | C74: SACO NEGRO ADM MUJER | D74: 35 | E74: 35 | F74: 37.5 | G74: =IF( OR(A74="",B74="",C74=""), "", CLEAN(TRIM(A74)) & "|" & CLEAN(TRIM(B74)) & "|" & CLEAN(TRIM(C74)) ) -> TARAPOTO|STAFF ADMINISTRATIVO|SACO NEGRO ADM MUJER
A75: TARAPOTO | B75: STAFF ADMINISTRATIVO | C75: POLO PIQUÉ PIZARRA RX, MANGA CORTA ADM | D75: =27/2 -> 13.5 | E75: =27/2 -> 13.5 | F75: =30/2 -> 15 | G75: =IF( OR(A75="",B75="",C75=""), "", CLEAN(TRIM(A75)) & "|" & CLEAN(TRIM(B75)) & "|" & CLEAN(TRIM(C75)) ) -> TARAPOTO|STAFF ADMINISTRATIVO|POLO PIQUÉ PIZARRA RX, MANGA CORTA ADM
A76: TARAPOTO | B76: STAFF ADMINISTRATIVO | C76: GORRO NEGRO ADM | D76: =10/2 -> 5 | E76: =10/2 -> 5 | F76: =10/2 -> 5 | G76: =IF( OR(A76="",B76="",C76=""), "", CLEAN(TRIM(A76)) & "|" & CLEAN(TRIM(B76)) & "|" & CLEAN(TRIM(C76)) ) -> TARAPOTO|STAFF ADMINISTRATIVO|GORRO NEGRO ADM
A77: TARAPOTO | B77: CAJA | C77: CAMISA A RALLAS AZUL | D77: =36/2 -> 18 | E77: =36/2 -> 18 | F77: =38/2 -> 19 | G77: =IF( OR(A77="",B77="",C77=""), "", CLEAN(TRIM(A77)) & "|" & CLEAN(TRIM(B77)) & "|" & CLEAN(TRIM(C77)) ) -> TARAPOTO|CAJA|CAMISA A RALLAS AZUL
A78: TARAPOTO | B78: CAJA | C78: PANTALÓN AZUL NOCHE | D78: =40/2 -> 20 | E78: =40/2 -> 20 | F78: =42/2 -> 21 | G78: =IF( OR(A78="",B78="",C78=""), "", CLEAN(TRIM(A78)) & "|" & CLEAN(TRIM(B78)) & "|" & CLEAN(TRIM(C78)) ) -> TARAPOTO|CAJA|PANTALÓN AZUL NOCHE
A79: TARAPOTO | B79: CAJA | C79: CHALECO AZUL NOCHE | D79: =35/2 -> 17.5 | E79: =35/2 -> 17.5 | F79: =37/2 -> 18.5 | G79: =IF( OR(A79="",B79="",C79=""), "", CLEAN(TRIM(A79)) & "|" & CLEAN(TRIM(B79)) & "|" & CLEAN(TRIM(C79)) ) -> TARAPOTO|CAJA|CHALECO AZUL NOCHE
A80: TARAPOTO | B80: CAJA | C80: SACO NEGRO CAJA HOMBRE | D80: 60 | E80: 60 | F80: 62.5 | G80: =IF( OR(A80="",B80="",C80=""), "", CLEAN(TRIM(A80)) & "|" & CLEAN(TRIM(B80)) & "|" & CLEAN(TRIM(C80)) ) -> TARAPOTO|CAJA|SACO NEGRO CAJA HOMBRE
A81: TARAPOTO | B81: CAJA | C81: BLUSA A RALLAS AZUL | D81: =36/2 -> 18 | E81: =36/2 -> 18 | F81: =38/2 -> 19 | G81: =IF( OR(A81="",B81="",C81=""), "", CLEAN(TRIM(A81)) & "|" & CLEAN(TRIM(B81)) & "|" & CLEAN(TRIM(C81)) ) -> TARAPOTO|CAJA|BLUSA A RALLAS AZUL
A82: TARAPOTO | B82: CAJA | C82: PANTALÓN AZUL NOCHE | D82: =40/2 -> 20 | E82: =40/2 -> 20 | F82: =42/2 -> 21 | G82: =IF( OR(A82="",B82="",C82=""), "", CLEAN(TRIM(A82)) & "|" & CLEAN(TRIM(B82)) & "|" & CLEAN(TRIM(C82)) ) -> TARAPOTO|CAJA|PANTALÓN AZUL NOCHE
A83: TARAPOTO | B83: CAJA | C83: CHALECO AZUL NOCHE | D83: =35/2 -> 17.5 | E83: =35/2 -> 17.5 | F83: =37/2 -> 18.5 | G83: =IF( OR(A83="",B83="",C83=""), "", CLEAN(TRIM(A83)) & "|" & CLEAN(TRIM(B83)) & "|" & CLEAN(TRIM(C83)) ) -> TARAPOTO|CAJA|CHALECO AZUL NOCHE
A84: TARAPOTO | B84: CAJA | C84: SACO NEGRO CAJA MUJER | D84: 35 | E84: 35 | F84: 37.5 | G84: =IF( OR(A84="",B84="",C84=""), "", CLEAN(TRIM(A84)) & "|" & CLEAN(TRIM(B84)) & "|" & CLEAN(TRIM(C84)) ) -> TARAPOTO|CAJA|SACO NEGRO CAJA MUJER
A85: TARAPOTO | B85: SEGURIDAD | C85: CAMISA CHARCOL MANGA LARGA | D85: =36/2 -> 18 | E85: =36/2 -> 18 | F85: =38/2 -> 19 | G85: =IF( OR(A85="",B85="",C85=""), "", CLEAN(TRIM(A85)) & "|" & CLEAN(TRIM(B85)) & "|" & CLEAN(TRIM(C85)) ) -> TARAPOTO|SEGURIDAD|CAMISA CHARCOL MANGA LARGA
A86: TARAPOTO | B86: SEGURIDAD | C86: GORRA NEGRA SEGURIDAD | D86: =10/2 -> 5 | E86: =10/2 -> 5 | F86: =10/2 -> 5 | G86: =IF( OR(A86="",B86="",C86=""), "", CLEAN(TRIM(A86)) & "|" & CLEAN(TRIM(B86)) & "|" & CLEAN(TRIM(C86)) ) -> TARAPOTO|SEGURIDAD|GORRA NEGRA SEGURIDAD
A87: TARAPOTO | B87: SEGURIDAD | C87: CASACA NEGRA SEGURIDAD | D87: 39 | E87: 39 | F87: 39 | G87: =IF( OR(A87="",B87="",C87=""), "", CLEAN(TRIM(A87)) & "|" & CLEAN(TRIM(B87)) & "|" & CLEAN(TRIM(C87)) ) -> TARAPOTO|SEGURIDAD|CASACA NEGRA SEGURIDAD
A88: TARAPOTO | B88: ANFITRIONAJE | C88: CAMISA COLOR NEGRO MANGA LARGA | D88: =36/2 -> 18 | E88: =36/2 -> 18 | F88: =38/2 -> 19 | G88: =IF( OR(A88="",B88="",C88=""), "", CLEAN(TRIM(A88)) & "|" & CLEAN(TRIM(B88)) & "|" & CLEAN(TRIM(C88)) ) -> TARAPOTO|ANFITRIONAJE|CAMISA COLOR NEGRO MANGA LARGA
A89: TARAPOTO | B89: ANFITRIONAJE | C89: SACO NEGRO ANFITRIONAJE HOMBRE | D89: 60 | E89: 60 | F89: 62.5 | G89: =IF( OR(A89="",B89="",C89=""), "", CLEAN(TRIM(A89)) & "|" & CLEAN(TRIM(B89)) & "|" & CLEAN(TRIM(C89)) ) -> TARAPOTO|ANFITRIONAJE|SACO NEGRO ANFITRIONAJE HOMBRE
A90: TARAPOTO | B90: ANFITRIONAJE | C90: BLUSA COLOR NEGRO MANGA LARGA | D90: =36/2 -> 18 | E90: =36/2 -> 18 | F90: =38/2 -> 19 | G90: =IF( OR(A90="",B90="",C90=""), "", CLEAN(TRIM(A90)) & "|" & CLEAN(TRIM(B90)) & "|" & CLEAN(TRIM(C90)) ) -> TARAPOTO|ANFITRIONAJE|BLUSA COLOR NEGRO MANGA LARGA
A91: TARAPOTO | B91: ANFITRIONAJE | C91: SACO NEGRO ANFITRIONAJE MUJER | D91: 35 | E91: 35 | F91: 37.5 | G91: =IF( OR(A91="",B91="",C91=""), "", CLEAN(TRIM(A91)) & "|" & CLEAN(TRIM(B91)) & "|" & CLEAN(TRIM(C91)) ) -> TARAPOTO|ANFITRIONAJE|SACO NEGRO ANFITRIONAJE MUJER
A92: TARAPOTO | B92: LIMPIEZA / MANTENIMIENTO | C92: PANTALÓN CARGO AZUL NOCHE | D92: =25/2 -> 12.5 | E92: =25/2 -> 12.5 | F92: =27/2 -> 13.5 | G92: =IF( OR(A92="",B92="",C92=""), "", CLEAN(TRIM(A92)) & "|" & CLEAN(TRIM(B92)) & "|" & CLEAN(TRIM(C92)) ) -> TARAPOTO|LIMPIEZA / MANTENIMIENTO|PANTALÓN CARGO AZUL NOCHE
A93: TARAPOTO | B93: LIMPIEZA / MANTENIMIENTO | C93: CHAQUETA AZUL NOCHE MANGA CORTA | D93: =28/2 -> 14 | E93: =28/2 -> 14 | F93: =30/2 -> 15 | G93: =IF( OR(A93="",B93="",C93=""), "", CLEAN(TRIM(A93)) & "|" & CLEAN(TRIM(B93)) & "|" & CLEAN(TRIM(C93)) ) -> TARAPOTO|LIMPIEZA / MANTENIMIENTO|CHAQUETA AZUL NOCHE MANGA CORTA
A94: TARAPOTO | B94: LIMPIEZA / MANTENIMIENTO | C94: POLO 30/1 GRIS | D94: =15/2 -> 7.5 | E94: =15/2 -> 7.5 | F94: =17/2 -> 8.5 | G94: =IF( OR(A94="",B94="",C94=""), "", CLEAN(TRIM(A94)) & "|" & CLEAN(TRIM(B94)) & "|" & CLEAN(TRIM(C94)) ) -> TARAPOTO|LIMPIEZA / MANTENIMIENTO|POLO 30/1 GRIS
A95: TARAPOTO | B95: BAR | C95: CAMISA NEGRA MANGA CORTA | D95: =33/2 -> 16.5 | E95: =33/2 -> 16.5 | F95: =35/2 -> 17.5 | G95: =IF( OR(A95="",B95="",C95=""), "", CLEAN(TRIM(A95)) & "|" & CLEAN(TRIM(B95)) & "|" & CLEAN(TRIM(C95)) ) -> TARAPOTO|BAR|CAMISA NEGRA MANGA CORTA
A96: TARAPOTO | B96: BAR | C96: PECHERA NEGRA CUERINA | D96: =39/2 -> 19.5 | E96: =39/2 -> 19.5 | F96: =39/2 -> 19.5 | G96: =IF( OR(A96="",B96="",C96=""), "", CLEAN(TRIM(A96)) & "|" & CLEAN(TRIM(B96)) & "|" & CLEAN(TRIM(C96)) ) -> TARAPOTO|BAR|PECHERA NEGRA CUERINA
A97: TARAPOTO | B97: BAR | C97: POLO 30/1 GRIS | D97: =15/2 -> 7.5 | E97: =15/2 -> 7.5 | F97: =17/2 -> 8.5 | G97: =IF( OR(A97="",B97="",C97=""), "", CLEAN(TRIM(A97)) & "|" & CLEAN(TRIM(B97)) & "|" & CLEAN(TRIM(C97)) ) -> TARAPOTO|BAR|POLO 30/1 GRIS
A98: TARAPOTO | B98: PRODUCCIÓN / COCINA | C98: PANTALÓN SAL Y PIMIENTA | D98: =22/2 -> 11 | E98: =22/2 -> 11 | F98: =23/2 -> 11.5 | G98: =IF( OR(A98="",B98="",C98=""), "", CLEAN(TRIM(A98)) & "|" & CLEAN(TRIM(B98)) & "|" & CLEAN(TRIM(C98)) ) -> TARAPOTO|PRODUCCIÓN / COCINA|PANTALÓN SAL Y PIMIENTA
A99: TARAPOTO | B99: PRODUCCIÓN / COCINA | C99: PECHERA GRIS EN DRILL | D99: =13/2 -> 6.5 | E99: =13/2 -> 6.5 | F99: =13/2 -> 6.5 | G99: =IF( OR(A99="",B99="",C99=""), "", CLEAN(TRIM(A99)) & "|" & CLEAN(TRIM(B99)) & "|" & CLEAN(TRIM(C99)) ) -> TARAPOTO|PRODUCCIÓN / COCINA|PECHERA GRIS EN DRILL
A100: TARAPOTO | B100: PRODUCCIÓN / COCINA | C100: GARIBALDI GRIS | D100: =9/2 -> 4.5 | E100: =9/2 -> 4.5 | F100: =9/2 -> 4.5 | G100: =IF( OR(A100="",B100="",C100=""), "", CLEAN(TRIM(A100)) & "|" & CLEAN(TRIM(B100)) & "|" & CLEAN(TRIM(C100)) ) -> TARAPOTO|PRODUCCIÓN / COCINA|GARIBALDI GRIS
...

Sheet Entradas
A1: Fecha | B1: LOCAL | C1: GRUPO (auto) | D1: CARGO ESTANDAR | E1: MATERIAL | F1: TALLA | G1: CANTIDAD
C2: {=IFERROR(_xlfn.XLOOKUP(B2,Locales!$A:$A,Locales!$B:$B,""),"")}
C3: {=IFERROR(_xlfn.XLOOKUP(B3,Locales!$A:$A,Locales!$B:$B,""),"")}
C4: {=IFERROR(_xlfn.XLOOKUP(B4,Locales!$A:$A,Locales!$B:$B,""),"")}
C5: {=IFERROR(_xlfn.XLOOKUP(B5,Locales!$A:$A,Locales!$B:$B,""),"")}
C6: {=IFERROR(_xlfn.XLOOKUP(B6,Locales!$A:$A,Locales!$B:$B,""),"")}
C7: {=IFERROR(_xlfn.XLOOKUP(B7,Locales!$A:$A,Locales!$B:$B,""),"")}
C8: {=IFERROR(_xlfn.XLOOKUP(B8,Locales!$A:$A,Locales!$B:$B,""),"")}
C9: {=IFERROR(_xlfn.XLOOKUP(B9,Locales!$A:$A,Locales!$B:$B,""),"")}
C10: {=IFERROR(_xlfn.XLOOKUP(B10,Locales!$A:$A,Locales!$B:$B,""),"")}
C11: {=IFERROR(_xlfn.XLOOKUP(B11,Locales!$A:$A,Locales!$B:$B,""),"")}
C12: {=IFERROR(_xlfn.XLOOKUP(B12,Locales!$A:$A,Locales!$B:$B,""),"")}
C13: {=IFERROR(_xlfn.XLOOKUP(B13,Locales!$A:$A,Locales!$B:$B,""),"")}
... C2000: {=IFERROR(_xlfn.XLOOKUP(B2000,Locales!$A:$A,Locales!$B:$B,""),"")}

Sheet Solicitudes
A1: Fecha | B1: DNI | C1: APELLIDOS Y NOMBRES (auto) | D1: LOCAL (auto) | E1: GRUPO (auto) | F1: CARGO ESTANDAR (auto) | G1: MATERIAL | H1: TALLA | I1: PRECIO (auto) | J1: CANTIDAD | K1: SUBTOTAL | L1: ESTADO | M1: Obs | N1: CLAVE
A2: 45974 | B2: 74415759 | C2: {=IFERROR(_xlfn.XLOOKUP(B2,Personal!$A:$A,Personal!$D:$D,""),"")} -> GONZALES LOZANO JAIME JUNIOR | D2: {=IFERROR(_xlfn.XLOOKUP(B2,Personal!$A:$A,Personal!$C:$C,""),"")} -> IQUITOS | E2: {=IFERROR(_xlfn.XLOOKUP(D2,Locales!$A:$A,Locales!$B:$B,""),"")} -> PATIO DE COMIDA | F2: {=IFERROR(_xlfn.XLOOKUP(B2,Personal!$A:$A,Personal!$F:$F,""),"")} -> CAJA | G2: POLO PIQUÉ CONCHE VINO, MANGA CORTA CAJA | H2: SML | I2: {=IFERROR(INDEX(Precios!$D:$F,MATCH(N2, Precios!$G:$G, 0),CHOOSE(MATCH(H2, {"SML";"XL";"XXL"}, 0), 1, 2, 3)), 0)} -> 13.5 | J2: 2 | K2: =IFERROR(I2*J2,0) -> 27 | L2: ENTREGADO | N2: =IF( OR(E2="",F2="",G2=""), "",CLEAN(TRIM(E2)) & "|" & CLEAN(TRIM(F2)) & "|" & CLEAN(TRIM(G2))) -> PATIO DE COMIDA|CAJA|POLO PIQUÉ CONCHE VINO, MANGA CORTA CAJA | O2: =IF(N2="","",IF(COUNTIF(Precios!$G:$G,N2)=0,"⚠ No coincide con Precios","OK")) -> OK
A3: 45974 | B3: 73233227 | C3: {=IFERROR(_xlfn.XLOOKUP(B3,Personal!$A:$A,Personal!$D:$D,""),"")} -> DEL CASTILLO TELLO JULIA OTILIA | D3: {=IFERROR(_xlfn.XLOOKUP(B3,Personal!$A:$A,Personal!$C:$C,""),"")} -> IQUITOS | E3: {=IFERROR(_xlfn.XLOOKUP(D3,Locales!$A:$A,Locales!$B:$B,""),"")} -> PATIO DE COMIDA | F3: {=IFERROR(_xlfn.XLOOKUP(B3,Personal!$A:$A,Personal!$F:$F,""),"")} -> COUNTER | G3: POLO PIQUÉ CONCHE VINO, MANGA CORTA COUNTER | H3: SML | I3: {=IFERROR(INDEX(Precios!$D:$F,MATCH(N3, Precios!$G:$G, 0),CHOOSE(MATCH(H3, {"SML";"XL";"XXL"}, 0), 1, 2, 3)), 0)} -> 13.5 | J3: 2 | K3: =IFERROR(I3*J3,0) -> 27 | L3: ENTREGADO | N3: =IF( OR(E3="",F3="",G3=""), "",CLEAN(TRIM(E3)) & "|" & CLEAN(TRIM(F3)) & "|" & CLEAN(TRIM(G3))) -> PATIO DE COMIDA|COUNTER|POLO PIQUÉ CONCHE VINO, MANGA CORTA COUNTER | O3: =IF(N3="","",IF(COUNTIF(Precios!$G:$G,N3)=0,"⚠ No coincide con Precios","OK")) -> OK
A4: 45974 | B4: 46192476 | C4: {=IFERROR(_xlfn.XLOOKUP(B4,Personal!$A:$A,Personal!$D:$D,""),"")} -> BABILONIA VEGA LINDA EBONY | D4: {=IFERROR(_xlfn.XLOOKUP(B4,Personal!$A:$A,Personal!$C:$C,""),"")} -> IQUITOS | E4: {=IFERROR(_xlfn.XLOOKUP(D4,Locales!$A:$A,Locales!$B:$B,""),"")} -> PATIO DE COMIDA | F4: {=IFERROR(_xlfn.XLOOKUP(B4,Personal!$A:$A,Personal!$F:$F,""),"")} -> COUNTER | G4: POLO PIQUÉ CONCHE VINO, MANGA CORTA COUNTER | H4: SML | I4: {=IFERROR(INDEX(Precios!$D:$F,MATCH(N4, Precios!$G:$G, 0),CHOOSE(MATCH(H4, {"SML";"XL";"XXL"}, 0), 1, 2, 3)), 0)} -> 13.5 | J4: 2 | K4: =IFERROR(I4*J4,0) -> 27 | L4: ENTREGADO | N4: =IF( OR(E4="",F4="",G4=""), "",CLEAN(TRIM(E4)) & "|" & CLEAN(TRIM(F4)) & "|" & CLEAN(TRIM(G4))) -> PATIO DE COMIDA|COUNTER|POLO PIQUÉ CONCHE VINO, MANGA CORTA COUNTER | O4: =IF(N4="","",IF(COUNTIF(Precios!$G:$G,N4)=0,"⚠ No coincide con Precios","OK")) -> OK
A5: 45974 | B5: 77100486 | C5: {=IFERROR(_xlfn.XLOOKUP(B5,Personal!$A:$A,Personal!$D:$D,""),"")} -> ALVAN ESCOBEDO ROSA DEL CARMEN | D5: {=IFERROR(_xlfn.XLOOKUP(B5,Personal!$A:$A,Personal!$C:$C,""),"")} -> IQUITOS | E5: {=IFERROR(_xlfn.XLOOKUP(D5,Locales!$A:$A,Locales!$B:$B,""),"")} -> PATIO DE COMIDA | F5: {=IFERROR(_xlfn.XLOOKUP(B5,Personal!$A:$A,Personal!$F:$F,""),"")} -> COUNTER | G5: POLO PIQUÉ CONCHE VINO, MANGA CORTA COUNTER | H5: SML | I5: {=IFERROR(INDEX(Precios!$D:$F,MATCH(N5, Precios!$G:$G, 0),CHOOSE(MATCH(H5, {"SML";"XL";"XXL"}, 0), 1, 2, 3)), 0)} -> 13.5 | J5: 2 | K5: =IFERROR(I5*J5,0) -> 27 | L5: ENTREGADO | N5: =IF( OR(E5="",F5="",G5=""), "",CLEAN(TRIM(E5)) & "|" & CLEAN(TRIM(F5)) & "|" & CLEAN(TRIM(G5))) -> PATIO DE COMIDA|COUNTER|POLO PIQUÉ CONCHE VINO, MANGA CORTA COUNTER | O5: =IF(N5="","",IF(COUNTIF(Precios!$G:$G,N5)=0,"⚠ No coincide con Precios","OK")) -> OK
A6: 45974 | B6: 43347817 | C6: {=IFERROR(_xlfn.XLOOKUP(B6,Personal!$A:$A,Personal!$D:$D,""),"")} -> SIAS MELENDEZ ROBIN | D6: {=IFERROR(_xlfn.XLOOKUP(B6,Personal!$A:$A,Personal!$C:$C,""),"")} -> IQUITOS | E6: {=IFERROR(_xlfn.XLOOKUP(D6,Locales!$A:$A,Locales!$B:$B,""),"")} -> PATIO DE COMIDA | F6: {=IFERROR(_xlfn.XLOOKUP(B6,Personal!$A:$A,Personal!$F:$F,""),"")} -> PRODUCCIÓN / COCINA | G6: CHAQUETA DRILL BLANCO | H6: SML | I6: {=IFERROR(INDEX(Precios!$D:$F,MATCH(N6, Precios!$G:$G, 0),CHOOSE(MATCH(H6, {"SML";"XL";"XXL"}, 0), 1, 2, 3)), 0)} -> 16.25 | J6: 2 | K6: =IFERROR(I6*J6,0) -> 32.5 | L6: ENTREGADO | N6: =IF( OR(E6="",F6="",G6=""), "",CLEAN(TRIM(E6)) & "|" & CLEAN(TRIM(F6)) & "|" & CLEAN(TRIM(G6))) -> PATIO DE COMIDA|PRODUCCIÓN / COCINA|CHAQUETA DRILL BLANCO | O6: =IF(N6="","",IF(COUNTIF(Precios!$G:$G,N6)=0,"⚠ No coincide con Precios","OK")) -> OK
A7: 45974 | B7: 43347817 | C7: {=IFERROR(_xlfn.XLOOKUP(B7,Personal!$A:$A,Personal!$D:$D,""),"")} -> SIAS MELENDEZ ROBIN | D7: {=IFERROR(_xlfn.XLOOKUP(B7,Personal!$A:$A,Personal!$C:$C,""),"")} -> IQUITOS | E7: {=IFERROR(_xlfn.XLOOKUP(D7,Locales!$A:$A,Locales!$B:$B,""),"")} -> PATIO DE COMIDA | F7: {=IFERROR(_xlfn.XLOOKUP(B7,Personal!$A:$A,Personal!$F:$F,""),"")} -> PRODUCCIÓN / COCINA | G7: PANTALÓN SAL Y PIMIENTA | H7: SML | I7: {=IFERROR(INDEX(Precios!$D:$F,MATCH(N7, Precios!$G:$G, 0),CHOOSE(MATCH(H7, {"SML";"XL";"XXL"}, 0), 1, 2, 3)), 0)} -> 11 | J7: 2 | K7: =IFERROR(I7*J7,0) -> 22 | L7: ENTREGADO | N7: =IF( OR(E7="",F7="",G7=""), "",CLEAN(TRIM(E7)) & "|" & CLEAN(TRIM(F7)) & "|" & CLEAN(TRIM(G7))) -> PATIO DE COMIDA|PRODUCCIÓN / COCINA|PANTALÓN SAL Y PIMIENTA | O7: =IF(N7="","",IF(COUNTIF(Precios!$G:$G,N7)=0,"⚠ No coincide con Precios","OK")) -> OK
A8: 45974 | B8: 43347817 | C8: {=IFERROR(_xlfn.XLOOKUP(B8,Personal!$A:$A,Personal!$D:$D,""),"")} -> SIAS MELENDEZ ROBIN | D8: {=IFERROR(_xlfn.XLOOKUP(B8,Personal!$A:$A,Personal!$C:$C,""),"")} -> IQUITOS | E8: {=IFERROR(_xlfn.XLOOKUP(D8,Locales!$A:$A,Locales!$B:$B,""),"")} -> PATIO DE COMIDA | F8: {=IFERROR(_xlfn.XLOOKUP(B8,Personal!$A:$A,Personal!$F:$F,""),"")} -> PRODUCCIÓN / COCINA | G8: PECHERA GRIS EN DRILL | H8: SML | I8: {=IFERROR(INDEX(Precios!$D:$F,MATCH(N8, Precios!$G:$G, 0),CHOOSE(MATCH(H8, {"SML";"XL";"XXL"}, 0), 1, 2, 3)), 0)} -> 6.5 | J8: 2 | K8: =IFERROR(I8*J8,0) -> 13 | L8: ENTREGADO | N8: =IF( OR(E8="",F8="",G8=""), "",CLEAN(TRIM(E8)) & "|" & CLEAN(TRIM(F8)) & "|" & CLEAN(TRIM(G8))) -> PATIO DE COMIDA|PRODUCCIÓN / COCINA|PECHERA GRIS EN DRILL | O8: =IF(N8="","",IF(COUNTIF(Precios!$G:$G,N8)=0,"⚠ No coincide con Precios","OK")) -> OK
A9: 45974 | B9: 43347817 | C9: {=IFERROR(_xlfn.XLOOKUP(B9,Personal!$A:$A,Personal!$D:$D,""),"")} -> SIAS MELENDEZ ROBIN | D9: {=IFERROR(_xlfn.XLOOKUP(B9,Personal!$A:$A,Personal!$C:$C,""),"")} -> IQUITOS | E9: {=IFERROR(_xlfn.XLOOKUP(D9,Locales!$A:$A,Locales!$B:$B,""),"")} -> PATIO DE COMIDA | F9: {=IFERROR(_xlfn.XLOOKUP(B9,Personal!$A:$A,Personal!$F:$F,""),"")} -> PRODUCCIÓN / COCINA | G9: GARIBALDI GRIS | H9: SML | I9: {=IFERROR(INDEX(Precios!$D:$F,MATCH(N9, Precios!$G:$G, 0),CHOOSE(MATCH(H9, {"SML";"XL";"XXL"}, 0), 1, 2, 3)), 0)} -> 4.5 | J9: 2 | K9: =IFERROR(I9*J9,0) -> 9 | L9: ENTREGADO | N9: =IF( OR(E9="",F9="",G9=""), "",CLEAN(TRIM(E9)) & "|" & CLEAN(TRIM(F9)) & "|" & CLEAN(TRIM(G9))) -> PATIO DE COMIDA|PRODUCCIÓN / COCINA|GARIBALDI GRIS | O9: =IF(N9="","",IF(COUNTIF(Precios!$G:$G,N9)=0,"⚠ No coincide con Precios","OK")) -> OK
A10: 45974 | B10: 43347817 | C10: {=IFERROR(_xlfn.XLOOKUP(B10,Personal!$A:$A,Personal!$D:$D,""),"")} -> SIAS MELENDEZ ROBIN | D10: {=IFERROR(_xlfn.XLOOKUP(B10,Personal!$A:$A,Personal!$C:$C,""),"")} -> IQUITOS | E10: {=IFERROR(_xlfn.XLOOKUP(D10,Locales!$A:$A,Locales!$B:$B,""),"")} -> PATIO DE COMIDA | F10: {=IFERROR(_xlfn.XLOOKUP(B10,Personal!$A:$A,Personal!$F:$F,""),"")} -> PRODUCCIÓN / COCINA | G10: POLO 30/1 GRIS | H10: SML | I10: {=IFERROR(INDEX(Precios!$D:$F,MATCH(N10, Precios!$G:$G, 0),CHOOSE(MATCH(H10, {"SML";"XL";"XXL"}, 0), 1, 2, 3)), 0)} -> 7.5 | J10: 4 | K10: =IFERROR(I10*J10,0) -> 30 | L10: ENTREGADO | N10: =IF( OR(E10="",F10="",G10=""), "",CLEAN(TRIM(E10)) & "|" & CLEAN(TRIM(F10)) & "|" & CLEAN(TRIM(G10))) -> PATIO DE COMIDA|PRODUCCIÓN / COCINA|POLO 30/1 GRIS | O10: =IF(N10="","",IF(COUNTIF(Precios!$G:$G,N10)=0,"⚠ No coincide con Precios","OK")) -> OK
A11: 45974 | B11: 62814712 | C11: {=IFERROR(_xlfn.XLOOKUP(B11,Personal!$A:$A,Personal!$D:$D,""),"")} -> PACAYA CHOTA MAYCOL | D11: {=IFERROR(_xlfn.XLOOKUP(B11,Personal!$A:$A,Personal!$C:$C,""),"")} -> IQUITOS | E11: {=IFERROR(_xlfn.XLOOKUP(D11,Locales!$A:$A,Locales!$B:$B,""),"")} -> PATIO DE COMIDA | F11: {=IFERROR(_xlfn.XLOOKUP(B11,Personal!$A:$A,Personal!$F:$F,""),"")} -> PRODUCCIÓN / COCINA | G11: CHAQUETA DRILL BLANCO | H11: SML | I11: {=IFERROR(INDEX(Precios!$D:$F,MATCH(N11, Precios!$G:$G, 0),CHOOSE(MATCH(H11, {"SML";"XL";"XXL"}, 0), 1, 2, 3)), 0)} -> 16.25 | J11: 2 | K11: =IFERROR(I11*J11,0) -> 32.5 | L11: ENTREGADO | N11: =IF( OR(E11="",F11="",G11=""), "",CLEAN(TRIM(E11)) & "|" & CLEAN(TRIM(F11)) & "|" & CLEAN(TRIM(G11))) -> PATIO DE COMIDA|PRODUCCIÓN / COCINA|CHAQUETA DRILL BLANCO | O11: =IF(N11="","",IF(COUNTIF(Precios!$G:$G,N11)=0,"⚠ No coincide con Precios","OK")) -> OK
A12: 45974 | B12: 62814712 | C12: {=IFERROR(_xlfn.XLOOKUP(B12,Personal!$A:$A,Personal!$D:$D,""),"")} -> PACAYA CHOTA MAYCOL | D12: {=IFERROR(_xlfn.XLOOKUP(B12,Personal!$A:$A,Personal!$C:$C,""),"")} -> IQUITOS | E12: {=IFERROR(_xlfn.XLOOKUP(D12,Locales!$A:$A,Locales!$B:$B,""),"")} -> PATIO DE COMIDA | F12: {=IFERROR(_xlfn.XLOOKUP(B12,Personal!$A:$A,Personal!$F:$F,""),"")} -> PRODUCCIÓN / COCINA | G12: PANTALÓN SAL Y PIMIENTA | H12: SML | I12: {=IFERROR(INDEX(Precios!$D:$F,MATCH(N12, Precios!$G:$G, 0),CHOOSE(MATCH(H12, {"SML";"XL";"XXL"}, 0), 1, 2, 3)), 0)} -> 11 | J12: 2 | K12: =IFERROR(I12*J12,0) -> 22 | L12: ENTREGADO | N12: =IF( OR(E12="",F12="",G12=""), "",CLEAN(TRIM(E12)) & "|" & CLEAN(TRIM(F12)) & "|" & CLEAN(TRIM(G12))) -> PATIO DE COMIDA|PRODUCCIÓN / COCINA|PANTALÓN SAL Y PIMIENTA | O12: =IF(N12="","",IF(COUNTIF(Precios!$G:$G,N12)=0,"⚠ No coincide con Precios","OK")) -> OK
A13: 45974 | B13: 62814712 | C13: {=IFERROR(_xlfn.XLOOKUP(B13,Personal!$A:$A,Personal!$D:$D,""),"")} -> PACAYA CHOTA MAYCOL | D13: {=IFERROR(_xlfn.XLOOKUP(B13,Personal!$A:$A,Personal!$C:$C,""),"")} -> IQUITOS | E13: {=IFERROR(_xlfn.XLOOKUP(D13,Locales!$A:$A,Locales!$B:$B,""),"")} -> PATIO DE COMIDA | F13: {=IFERROR(_xlfn.XLOOKUP(B13,Personal!$A:$A,Personal!$F:$F,""),"")} -> PRODUCCIÓN / COCINA | G13: PECHERA GRIS EN DRILL | H13: SML | I13: {=IFERROR(INDEX(Precios!$D:$F,MATCH(N13, Precios!$G:$G, 0),CHOOSE(MATCH(H13, {"SML";"XL";"XXL"}, 0), 1, 2, 3)), 0)} -> 6.5 | J13: 2 | K13: =IFERROR(I13*J13,0) -> 13 | L13: ENTREGADO | N13: =IF( OR(E13="",F13="",G13=""), "",CLEAN(TRIM(E13)) & "|" & CLEAN(TRIM(F13)) & "|" & CLEAN(TRIM(G13))) -> PATIO DE COMIDA|PRODUCCIÓN / COCINA|PECHERA GRIS EN DRILL | O13: =IF(N13="","",IF(COUNTIF(Precios!$G:$G,N13)=0,"⚠ No coincide con Precios","OK")) -> OK
... A116: 45987 | B116: 61053284 | C116: {=IFERROR(_xlfn.XLOOKUP(B116,Personal!$A:$A,Personal!$D:$D,""),"")} -> GUERRERO NAVARRO WEISSER MANUEL | D116: {=IFERROR(_xlfn.XLOOKUP(B116,Personal!$A:$A,Personal!$C:$C,""),"")} -> MIRAFLORES | E116: {=IFERROR(_xlfn.XLOOKUP(D116,Locales!$A:$A,Locales!$B:$B,""),"")} -> LIMA E ICA PROVINCIA | F116: {=IFERROR(_xlfn.XLOOKUP(B116,Personal!$A:$A,Personal!$F:$F,""),"")} -> PRODUCCIÓN / COCINA | G116: POLO 30/1 GRIS | H116: SML | I116: {=IFERROR(INDEX(Precios!$D:$F,MATCH(N116, Precios!$G:$G, 0),CHOOSE(MATCH(H116, {"SML";"XL";"XXL"}, 0), 1, 2, 3)), 0)} -> 7.5 | J116: 2 | K116: =IFERROR(I116*J116,0) -> 15 | L116: ENTREGADO | N116: =IF( OR(E116="",F116="",G116=""), "",CLEAN(TRIM(E116)) & "|" & CLEAN(TRIM(F116)) & "|" & CLEAN(TRIM(G116))) -> LIMA E ICA PROVINCIA|PRODUCCIÓN / COCINA|POLO 30/1 GRIS | O116: =IF(N116="","",IF(COUNTIF(Precios!$G:$G,N116)=0,"⚠ No coincide con Precios","OK")) -> OK
A117: 45975 | B117: 46722628 | C117: {=IFERROR(_xlfn.XLOOKUP(B117,Personal!$A:$A,Personal!$D:$D,""),"")} -> REYES RAMIREZ DIANA YOLI | D117: {=IFERROR(_xlfn.XLOOKUP(B117,Personal!$A:$A,Personal!$C:$C,""),"")} -> LARCOMAR | E117: {=IFERROR(_xlfn.XLOOKUP(D117,Locales!$A:$A,Locales!$B:$B,""),"")} -> PATIO DE COMIDA | F117: {=IFERROR(_xlfn.XLOOKUP(B117,Personal!$A:$A,Personal!$F:$F,""),"")} -> STAFF ADMINISTRATIVO | G117: POLO PIQUÉ PIZARRA RX, MANGA CORTA ADMI | H117: SML | I117: {=IFERROR(INDEX(Precios!$D:$F,MATCH(N117, Precios!$G:$G, 0),CHOOSE(MATCH(H117, {"SML";"XL";"XXL"}, 0), 1, 2, 3)), 0)} -> 15 | J117: 2 | K117: =IFERROR(I117*J117,0) -> 30 | L117: ENTREGADO | N117: =IF( OR(E117="",F117="",G117=""), "",CLEAN(TRIM(E117)) & "|" & CLEAN(TRIM(F117)) & "|" & CLEAN(TRIM(G117))) -> PATIO DE COMIDA|STAFF ADMINISTRATIVO|POLO PIQUÉ PIZARRA RX, MANGA CORTA ADMI | O117: =IF(N117="","",IF(COUNTIF(Precios!$G:$G,N117)=0,"⚠ No coincide con Precios","OK")) -> OK
A118: 45975 | B118: 46722628 | C118: {=IFERROR(_xlfn.XLOOKUP(B118,Personal!$A:$A,Personal!$D:$D,""),"")} -> REYES RAMIREZ DIANA YOLI | D118: {=IFERROR(_xlfn.XLOOKUP(B118,Personal!$A:$A,Personal!$C:$C,""),"")} -> LARCOMAR | E118: {=IFERROR(_xlfn.XLOOKUP(D118,Locales!$A:$A,Locales!$B:$B,""),"")} -> PATIO DE COMIDA | F118: {=IFERROR(_xlfn.XLOOKUP(B118,Personal!$A:$A,Personal!$F:$F,""),"")} -> STAFF ADMINISTRATIVO | G118: GORRO NEGRO ADM | H118: SML | I118: {=IFERROR(INDEX(Precios!$D:$F,MATCH(N118, Precios!$G:$G, 0),CHOOSE(MATCH(H118, {"SML";"XL";"XXL"}, 0), 1, 2, 3)), 0)} -> 5 | J118: 2 | K118: =IFERROR(I118*J118,0) -> 10 | L118: ENTREGADO | N118: =IF( OR(E118="",F118="",G118=""), "",CLEAN(TRIM(E118)) & "|" & CLEAN(TRIM(F118)) & "|" & CLEAN(TRIM(G118))) -> PATIO DE COMIDA|STAFF ADMINISTRATIVO|GORRO NEGRO ADM | O118: =IF(N118="","",IF(COUNTIF(Precios!$G:$G,N118)=0,"⚠ No coincide con Precios","OK")) -> OK
A119: 45975 | B119: 72670432 | C119: {=IFERROR(_xlfn.XLOOKUP(B119,Personal!$A:$A,Personal!$D:$D,""),"")} -> PAREDES MAGUIÑA HUGO RAFAEL | D119: {=IFERROR(_xlfn.XLOOKUP(B119,Personal!$A:$A,Personal!$C:$C,""),"")} -> LARCOMAR | E119: {=IFERROR(_xlfn.XLOOKUP(D119,Locales!$A:$A,Locales!$B:$B,""),"")} -> PATIO DE COMIDA | F119: {=IFERROR(_xlfn.XLOOKUP(B119,Personal!$A:$A,Personal!$F:$F,""),"")} -> STAFF ADMINISTRATIVO | G119: GORRO NEGRO ADM | H119: SML | I119: {=IFERROR(INDEX(Precios!$D:$F,MATCH(N119, Precios!$G:$G, 0),CHOOSE(MATCH(H119, {"SML";"XL";"XXL"}, 0), 1, 2, 3)), 0)} -> 5 | J119: 2 | K119: =IFERROR(I119*J119,0) -> 10 | L119: ENTREGADO | N119: =IF( OR(E119="",F119="",G119=""), "",CLEAN(TRIM(E119)) & "|" & CLEAN(TRIM(F119)) & "|" & CLEAN(TRIM(G119))) -> PATIO DE COMIDA|STAFF ADMINISTRATIVO|GORRO NEGRO ADM | O119: =IF(N119="","",IF(COUNTIF(Precios!$G:$G,N119)=0,"⚠ No coincide con Precios","OK")) -> OK
A120: 45902 | B120: 41983477 | C120: {=IFERROR(_xlfn.XLOOKUP(B120,Personal!$A:$A,Personal!$D:$D,""),"")} -> ZAPATA HERRERA FRANKLYN RICARDO | D120: {=IFERROR(_xlfn.XLOOKUP(B120,Personal!$A:$A,Personal!$C:$C,""),"")} -> JESUS MARIA | E120: {=IFERROR(_xlfn.XLOOKUP(D120,Locales!$A:$A,Locales!$B:$B,""),"")} -> LIMA E ICA PROVINCIA | F120: {=IFERROR(_xlfn.XLOOKUP(B120,Personal!$A:$A,Personal!$F:$F,""),"")} -> MOZO | G120: CAMISA BLANCA (MANGA LARGA) | H120: SML | I120: {=IFERROR(INDEX(Precios!$D:$F,MATCH(N120, Precios!$G:$G, 0),CHOOSE(MATCH(H120, {"SML";"XL";"XXL"}, 0), 1, 2, 3)), 0)} -> 18.5 | J120: 2 | K120: =IFERROR(I120*J120,0) -> 37 | L120: ENTREGADO | N120: =IF( OR(E120="",F120="",G120=""), "",CLEAN(TRIM(E120)) & "|" & CLEAN(TRIM(F120)) & "|" & CLEAN(TRIM(G120))) -> LIMA E ICA PROVINCIA|MOZO|CAMISA BLANCA (MANGA LARGA) | O120: =IF(N120="","",IF(COUNTIF(Precios!$G:$G,N120)=0,"⚠ No coincide con Precios","OK")) -> OK
A121: 45902 | B121: 41983477 | C121: {=IFERROR(_xlfn.XLOOKUP(B121,Personal!$A:$A,Personal!$D:$D,""),"")} -> ZAPATA HERRERA FRANKLYN RICARDO | D121: {=IFERROR(_xlfn.XLOOKUP(B121,Personal!$A:$A,Personal!$C:$C,""),"")} -> JESUS MARIA | E121: {=IFERROR(_xlfn.XLOOKUP(D121,Locales!$A:$A,Locales!$B:$B,""),"")} -> LIMA E ICA PROVINCIA | F121: {=IFERROR(_xlfn.XLOOKUP(B121,Personal!$A:$A,Personal!$F:$F,""),"")} -> MOZO | G121: MANDILON DRILL NEGRO | H121: SML | I121: {=IFERROR(INDEX(Precios!$D:$F,MATCH(N121, Precios!$G:$G, 0),CHOOSE(MATCH(H121, {"SML";"XL";"XXL"}, 0), 1, 2, 3)), 0)} -> 7 | J121: 2 | K121: =IFERROR(I121*J121,0) -> 14 | L121: ENTREGADO | N121: =IF( OR(E121="",F121="",G121=""), "",CLEAN(TRIM(E121)) & "|" & CLEAN(TRIM(F121)) & "|" & CLEAN(TRIM(G121))) -> LIMA E ICA PROVINCIA|MOZO|MANDILON DRILL NEGRO | O121: =IF(N121="","",IF(COUNTIF(Precios!$G:$G,N121)=0,"⚠ No coincide con Precios","OK")) -> OK
A122: 45902 | B122: 41983477 | C122: {=IFERROR(_xlfn.XLOOKUP(B122,Personal!$A:$A,Personal!$D:$D,""),"")} -> ZAPATA HERRERA FRANKLYN RICARDO | D122: {=IFERROR(_xlfn.XLOOKUP(B122,Personal!$A:$A,Personal!$C:$C,""),"")} -> JESUS MARIA | E122: {=IFERROR(_xlfn.XLOOKUP(D122,Locales!$A:$A,Locales!$B:$B,""),"")} -> LIMA E ICA PROVINCIA | F122: {=IFERROR(_xlfn.XLOOKUP(B122,Personal!$A:$A,Personal!$F:$F,""),"")} -> MOZO | G122: ANDARIN GRANATE | H122: SML | I122: {=IFERROR(INDEX(Precios!$D:$F,MATCH(N122, Precios!$G:$G, 0),CHOOSE(MATCH(H122, {"SML";"XL";"XXL"}, 0), 1, 2, 3)), 0)} -> 1.75 | J122: 2 | K122: =IFERROR(I122*J122,0) -> 3.5 | L122: ENTREGADO | N122: =IF( OR(E122="",F122="",G122=""), "",CLEAN(TRIM(E122)) & "|" & CLEAN(TRIM(F122)) & "|" & CLEAN(TRIM(G122))) -> LIMA E ICA PROVINCIA|MOZO|ANDARIN GRANATE | O122: =IF(N122="","",IF(COUNTIF(Precios!$G:$G,N122)=0,"⚠ No coincide con Precios","OK")) -> OK
A123: 45973 | B123: 47115854 | C123: {=IFERROR(_xlfn.XLOOKUP(B123,Personal!$A:$A,Personal!$D:$D,""),"")} -> JULCA DIAZ EDGAR | D123: {=IFERROR(_xlfn.XLOOKUP(B123,Personal!$A:$A,Personal!$C:$C,""),"")} -> JESUS MARIA | E123: {=IFERROR(_xlfn.XLOOKUP(D123,Locales!$A:$A,Locales!$B:$B,""),"")} -> LIMA E ICA PROVINCIA | F123: {=IFERROR(_xlfn.XLOOKUP(B123,Personal!$A:$A,Personal!$F:$F,""),"")} -> PRODUCCIÓN / COCINA | G123: CHAQUETA DRILL BLANCO | H123: SML | I123: {=IFERROR(INDEX(Precios!$D:$F,MATCH(N123, Precios!$G:$G, 0),CHOOSE(MATCH(H123, {"SML";"XL";"XXL"}, 0), 1, 2, 3)), 0)} -> 16.25 | J123: 2 | K123: =IFERROR(I123*J123,0) -> 32.5 | L123: ENTREGADO | N123: =IF( OR(E123="",F123="",G123=""), "",CLEAN(TRIM(E123)) & "|" & CLEAN(TRIM(F123)) & "|" & CLEAN(TRIM(G123))) -> LIMA E ICA PROVINCIA|PRODUCCIÓN / COCINA|CHAQUETA DRILL BLANCO | O123: =IF(N123="","",IF(COUNTIF(Precios!$G:$G,N123)=0,"⚠ No coincide con Precios","OK")) -> OK
A124: 45973 | B124: 47115854 | C124: {=IFERROR(_xlfn.XLOOKUP(B124,Personal!$A:$A,Personal!$D:$D,""),"")} -> JULCA DIAZ EDGAR | D124: {=IFERROR(_xlfn.XLOOKUP(B124,Personal!$A:$A,Personal!$C:$C,""),"")} -> JESUS MARIA | E124: {=IFERROR(_xlfn.XLOOKUP(D124,Locales!$A:$A,Locales!$B:$B,""),"")} -> LIMA E ICA PROVINCIA | F124: {=IFERROR(_xlfn.XLOOKUP(B124,Personal!$A:$A,Personal!$F:$F,""),"")} -> PRODUCCIÓN / COCINA | G124: PANTALÓN SAL Y PIMIENTA | H124: SML | I124: {=IFERROR(INDEX(Precios!$D:$F,MATCH(N124, Precios!$G:$G, 0),CHOOSE(MATCH(H124, {"SML";"XL";"XXL"}, 0), 1, 2, 3)), 0)} -> 11 | J124: 2 | K124: =IFERROR(I124*J124,0) -> 22 | L124: ENTREGADO | N124: =IF( OR(E124="",F124="",G124=""), "",CLEAN(TRIM(E124)) & "|" & CLEAN(TRIM(F124)) & "|" & CLEAN(TRIM(G124))) -> LIMA E ICA PROVINCIA|PRODUCCIÓN / COCINA|PANTALÓN SAL Y PIMIENTA | O124: =IF(N124="","",IF(COUNTIF(Precios!$G:$G,N124)=0,"⚠ No coincide con Precios","OK")) -> OK
A125: 45973 | B125: 47115854 | C125: {=IFERROR(_xlfn.XLOOKUP(B125,Personal!$A:$A,Personal!$D:$D,""),"")} -> JULCA DIAZ EDGAR | D125: {=IFERROR(_xlfn.XLOOKUP(B125,Personal!$A:$A,Personal!$C:$C,""),"")} -> JESUS MARIA | E125: {=IFERROR(_xlfn.XLOOKUP(D125,Locales!$A:$A,Locales!$B:$B,""),"")} -> LIMA E ICA PROVINCIA | F125: {=IFERROR(_xlfn.XLOOKUP(B125,Personal!$A:$A,Personal!$F:$F,""),"")} -> PRODUCCIÓN / COCINA | G125: PECHERA GRIS EN DRILL | H125: SML | I125: {=IFERROR(INDEX(Precios!$D:$F,MATCH(N125, Precios!$G:$G, 0),CHOOSE(MATCH(H125, {"SML";"XL";"XXL"}, 0), 1, 2, 3)), 0)} -> 6.5 | J125: 2 | K125: =IFERROR(I125*J125,0) -> 13 | L125: ENTREGADO | N125: =IF( OR(E125="",F125="",G125=""), "",CLEAN(TRIM(E125)) & "|" & CLEAN(TRIM(F125)) & "|" & CLEAN(TRIM(G125))) -> LIMA E ICA PROVINCIA|PRODUCCIÓN / COCINA|PECHERA GRIS EN DRILL | O125: =IF(N125="","",IF(COUNTIF(Precios!$G:$G,N125)=0,"⚠ No coincide con Precios","OK")) -> OK
A126: 45973 | B126: 47115854 | C126: {=IFERROR(_xlfn.XLOOKUP(B126,Personal!$A:$A,Personal!$D:$D,""),"")} -> JULCA DIAZ EDGAR | D126: {=IFERROR(_xlfn.XLOOKUP(B126,Personal!$A:$A,Personal!$C:$C,""),"")} -> JESUS MARIA | E126: {=IFERROR(_xlfn.XLOOKUP(D126,Locales!$A:$A,Locales!$B:$B,""),"")} -> LIMA E ICA PROVINCIA | F126: {=IFERROR(_xlfn.XLOOKUP(B126,Personal!$A:$A,Personal!$F:$F,""),"")} -> PRODUCCIÓN / COCINA | G126: GARIBALDI GRIS | H126: SML | I126: {=IFERROR(INDEX(Precios!$D:$F,MATCH(N126, Precios!$G:$G, 0),CHOOSE(MATCH(H126, {"SML";"XL";"XXL"}, 0), 1, 2, 3)), 0)} -> 4.5 | J126: 2 | K126: =IFERROR(I126*J126,0) -> 9 | L126: ENTREGADO | N126: =IF( OR(E126="",F126="",G126=""), "",CLEAN(TRIM(E126)) & "|" & CLEAN(TRIM(F126)) & "|" & CLEAN(TRIM(G126))) -> LIMA E ICA PROVINCIA|PRODUCCIÓN / COCINA|GARIBALDI GRIS | O126: =IF(N126="","",IF(COUNTIF(Precios!$G:$G,N126)=0,"⚠ No coincide con Precios","OK")) -> OK
A127: 45973 | B127: 47115854 | C127: {=IFERROR(_xlfn.XLOOKUP(B127,Personal!$A:$A,Personal!$D:$D,""),"")} -> JULCA DIAZ EDGAR | D127: {=IFERROR(_xlfn.XLOOKUP(B127,Personal!$A:$A,Personal!$C:$C,""),"")} -> JESUS MARIA | E127: {=IFERROR(_xlfn.XLOOKUP(D127,Locales!$A:$A,Locales!$B:$B,""),"")} -> LIMA E ICA PROVINCIA | F127: {=IFERROR(_xlfn.XLOOKUP(B127,Personal!$A:$A,Personal!$F:$F,""),"")} -> PRODUCCIÓN / COCINA | G127: POLO 30/1 GRIS | H127: SML | I127: {=IFERROR(INDEX(Precios!$D:$F,MATCH(N127, Precios!$G:$G, 0),CHOOSE(MATCH(H127, {"SML";"XL";"XXL"}, 0), 1, 2, 3)), 0)} -> 7.5 | J127: 2 | K127: =IFERROR(I127*J127,0) -> 15 | L127: ENTREGADO | N127: =IF( OR(E127="",F127="",G127=""), "",CLEAN(TRIM(E127)) & "|" & CLEAN(TRIM(F127)) & "|" & CLEAN(TRIM(G127))) -> LIMA E ICA PROVINCIA|PRODUCCIÓN / COCINA|POLO 30/1 GRIS | O127: =IF(N127="","",IF(COUNTIF(Precios!$G:$G,N127)=0,"⚠ No coincide con Precios","OK")) -> OK
A128: 45943 | B128: 32933368 | C128: {=IFERROR(_xlfn.XLOOKUP(B128,Personal!$A:$A,Personal!$D:$D,""),"")} -> MUÑOZ TORRES MARTHA YNES | D128: {=IFERROR(_xlfn.XLOOKUP(B128,Personal!$A:$A,Personal!$C:$C,""),"")} -> JESUS MARIA | E128: {=IFERROR(_xlfn.XLOOKUP(D128,Locales!$A:$A,Locales!$B:$B,""),"")} -> LIMA E ICA PROVINCIA | F128: {=IFERROR(_xlfn.XLOOKUP(B128,Personal!$A:$A,Personal!$F:$F,""),"")} -> PRODUCCIÓN / COCINA | G128: CHAQUETA DRILL BLANCO | H128: SML | I128: {=IFERROR(INDEX(Precios!$D:$F,MATCH(N128, Precios!$G:$G, 0),CHOOSE(MATCH(H128, {"SML";"XL";"XXL"}, 0), 1, 2, 3)), 0)} -> 16.25 | J128: 2 | K128: =IFERROR(I128*J128,0) -> 32.5 | L128: ENTREGADO | N128: =IF( OR(E128="",F128="",G128=""), "",CLEAN(TRIM(E128)) & "|" & CLEAN(TRIM(F128)) & "|" & CLEAN(TRIM(G128))) -> LIMA E ICA PROVINCIA|PRODUCCIÓN / COCINA|CHAQUETA DRILL BLANCO | O128: =IF(N128="","",IF(COUNTIF(Precios!$G:$G,N128)=0,"⚠ No coincide con Precios","OK")) -> OK
A129: 45943 | B129: 32933368 | C129: {=IFERROR(_xlfn.XLOOKUP(B129,Personal!$A:$A,Personal!$D:$D,""),"")} -> MUÑOZ TORRES MARTHA YNES | D129: {=IFERROR(_xlfn.XLOOKUP(B129,Personal!$A:$A,Personal!$C:$C,""),"")} -> JESUS MARIA | E129: {=IFERROR(_xlfn.XLOOKUP(D129,Locales!$A:$A,Locales!$B:$B,""),"")} -> LIMA E ICA PROVINCIA | F129: {=IFERROR(_xlfn.XLOOKUP(B129,Personal!$A:$A,Personal!$F:$F,""),"")} -> PRODUCCIÓN / COCINA | G129: PANTALÓN SAL Y PIMIENTA | H129: SML | I129: {=IFERROR(INDEX(Precios!$D:$F,MATCH(N129, Precios!$G:$G, 0),CHOOSE(MATCH(H129, {"SML";"XL";"XXL"}, 0), 1, 2, 3)), 0)} -> 11 | J129: 2 | K129: =IFERROR(I129*J129,0) -> 22 | L129: ENTREGADO | N129: =IF( OR(E129="",F129="",G129=""), "",CLEAN(TRIM(E129)) & "|" & CLEAN(TRIM(F129)) & "|" & CLEAN(TRIM(G129))) -> LIMA E ICA PROVINCIA|PRODUCCIÓN / COCINA|PANTALÓN SAL Y PIMIENTA | O129: =IF(N129="","",IF(COUNTIF(Precios!$G:$G,N129)=0,"⚠ No coincide con Precios","OK")) -> OK
A130: 45943 | B130: 32933368 | C130: {=IFERROR(_xlfn.XLOOKUP(B130,Personal!$A:$A,Personal!$D:$D,""),"")} -> MUÑOZ TORRES MARTHA YNES | D130: {=IFERROR(_xlfn.XLOOKUP(B130,Personal!$A:$A,Personal!$C:$C,""),"")} -> JESUS MARIA | E130: {=IFERROR(_xlfn.XLOOKUP(D130,Locales!$A:$A,Locales!$B:$B,""),"")} -> LIMA E ICA PROVINCIA | F130: {=IFERROR(_xlfn.XLOOKUP(B130,Personal!$A:$A,Personal!$F:$F,""),"")} -> PRODUCCIÓN / COCINA | G130: PECHERA GRIS EN DRILL | H130: SML | I130: {=IFERROR(INDEX(Precios!$D:$F,MATCH(N130, Precios!$G:$G, 0),CHOOSE(MATCH(H130, {"SML";"XL";"XXL"}, 0), 1, 2, 3)), 0)} -> 6.5 | J130: 2 | K130: =IFERROR(I130*J130,0) -> 13 | L130: ENTREGADO | N130: =IF( OR(E130="",F130="",G130=""), "",CLEAN(TRIM(E130)) & "|" & CLEAN(TRIM(F130)) & "|" & CLEAN(TRIM(G130))) -> LIMA E ICA PROVINCIA|PRODUCCIÓN / COCINA|PECHERA GRIS EN DRILL | O130: =IF(N130="","",IF(COUNTIF(Precios!$G:$G,N130)=0,"⚠ No coincide con Precios","OK")) -> OK
... A215: 46010 | B215: 46831171 | C215: {=IFERROR(_xlfn.XLOOKUP(B215,Personal!$A:$A,Personal!$D:$D,""),"")} -> SANCHEZ LLOCLLA ROGER YAISON | D215: {=IFERROR(_xlfn.XLOOKUP(B215,Personal!$A:$A,Personal!$C:$C,""),"")} -> VCH-ADM | E215: {=IFERROR(_xlfn.XLOOKUP(D215,Locales!$A:$A,Locales!$B:$B,""),"")} -> LIMA E ICA PROVINCIA | F215: {=IFERROR(_xlfn.XLOOKUP(B215,Personal!$A:$A,Personal!$F:$F,""),"")} -> BAR | G215: POLO 30/1 GRIS | H215: SML | I215: {=IFERROR(INDEX(Precios!$D:$F,MATCH(N215, Precios!$G:$G, 0),CHOOSE(MATCH(H215, {"SML";"XL";"XXL"}, 0), 1, 2, 3)), 0)} -> 7.5 | J215: 2 | K215: =IFERROR(I215*J215,0) -> 15 | L215: ENTREGADO | N215: =IF( OR(E215="",F215="",G215=""), "",CLEAN(TRIM(E215)) & "|" & CLEAN(TRIM(F215)) & "|" & CLEAN(TRIM(G215))) -> LIMA E ICA PROVINCIA|BAR|POLO 30/1 GRIS | O215: =IF(N215="","",IF(COUNTIF(Precios!$G:$G,N215)=0,"⚠ No coincide con Precios","OK")) -> OK
C216: {=IFERROR(_xlfn.XLOOKUP(B216,Personal!$A:$A,Personal!$D:$D,""),"")} -> 0 | D216: {=IFERROR(_xlfn.XLOOKUP(B216,Personal!$A:$A,Personal!$C:$C,""),"")} -> 0 | E216: {=IFERROR(_xlfn.XLOOKUP(D216,Locales!$A:$A,Locales!$B:$B,""),"")} | F216: {=IFERROR(_xlfn.XLOOKUP(B216,Personal!$A:$A,Personal!$F:$F,""),"")} -> 0 | I216: {=IFERROR(INDEX(Precios!$D:$F,MATCH(N216, Precios!$G:$G, 0),CHOOSE(MATCH(H216, {"SML";"XL";"XXL"}, 0), 1, 2, 3)), 0)} -> 0 | K216: =IFERROR(I216*J216,0) -> 0 | N216: =IF( OR(E216="",F216="",G216=""), "",CLEAN(TRIM(E216)) & "|" & CLEAN(TRIM(F216)) & "|" & CLEAN(TRIM(G216))) | O216: =IF(N216="","",IF(COUNTIF(Precios!$G:$G,N216)=0,"⚠ No coincide con Precios","OK"))
C217: {=IFERROR(_xlfn.XLOOKUP(B217,Personal!$A:$A,Personal!$D:$D,""),"")} -> 0 | D217: {=IFERROR(_xlfn.XLOOKUP(B217,Personal!$A:$A,Personal!$C:$C,""),"")} -> 0 | E217: {=IFERROR(_xlfn.XLOOKUP(D217,Locales!$A:$A,Locales!$B:$B,""),"")} | F217: {=IFERROR(_xlfn.XLOOKUP(B217,Personal!$A:$A,Personal!$F:$F,""),"")} -> 0 | I217: {=IFERROR(INDEX(Precios!$D:$F,MATCH(N217, Precios!$G:$G, 0),CHOOSE(MATCH(H217, {"SML";"XL";"XXL"}, 0), 1, 2, 3)), 0)} -> 0 | K217: =IFERROR(I217*J217,0) -> 0 | N217: =IF( OR(E217="",F217="",G217=""), "",CLEAN(TRIM(E217)) & "|" & CLEAN(TRIM(F217)) & "|" & CLEAN(TRIM(G217))) | O217: =IF(N217="","",IF(COUNTIF(Precios!$G:$G,N217)=0,"⚠ No coincide con Precios","OK"))
C218: {=IFERROR(_xlfn.XLOOKUP(B218,Personal!$A:$A,Personal!$D:$D,""),"")} -> 0 | D218: {=IFERROR(_xlfn.XLOOKUP(B218,Personal!$A:$A,Personal!$C:$C,""),"")} -> 0 | E218: {=IFERROR(_xlfn.XLOOKUP(D218,Locales!$A:$A,Locales!$B:$B,""),"")} | F218: {=IFERROR(_xlfn.XLOOKUP(B218,Personal!$A:$A,Personal!$F:$F,""),"")} -> 0 | I218: {=IFERROR(INDEX(Precios!$D:$F,MATCH(N218, Precios!$G:$G, 0),CHOOSE(MATCH(H218, {"SML";"XL";"XXL"}, 0), 1, 2, 3)), 0)} -> 0 | K218: =IFERROR(I218*J218,0) -> 0 | N218: =IF( OR(E218="",F218="",G218=""), "",CLEAN(TRIM(E218)) & "|" & CLEAN(TRIM(F218)) & "|" & CLEAN(TRIM(G218))) | O218: =IF(N218="","",IF(COUNTIF(Precios!$G:$G,N218)=0,"⚠ No coincide con Precios","OK"))
C219: {=IFERROR(_xlfn.XLOOKUP(B219,Personal!$A:$A,Personal!$D:$D,""),"")} -> 0 | D219: {=IFERROR(_xlfn.XLOOKUP(B219,Personal!$A:$A,Personal!$C:$C,""),"")} -> 0 | E219: {=IFERROR(_xlfn.XLOOKUP(D219,Locales!$A:$A,Locales!$B:$B,""),"")} | F219: {=IFERROR(_xlfn.XLOOKUP(B219,Personal!$A:$A,Personal!$F:$F,""),"")} -> 0 | I219: {=IFERROR(INDEX(Precios!$D:$F,MATCH(N219, Precios!$G:$G, 0),CHOOSE(MATCH(H219, {"SML";"XL";"XXL"}, 0), 1, 2, 3)), 0)} -> 0 | K219: =IFERROR(I219*J219,0) -> 0 | N219: =IF( OR(E219="",F219="",G219=""), "",CLEAN(TRIM(E219)) & "|" & CLEAN(TRIM(F219)) & "|" & CLEAN(TRIM(G219))) | O219: =IF(N219="","",IF(COUNTIF(Precios!$G:$G,N219)=0,"⚠ No coincide con Precios","OK"))
C220: {=IFERROR(_xlfn.XLOOKUP(B220,Personal!$A:$A,Personal!$D:$D,""),"")} -> 0 | D220: {=IFERROR(_xlfn.XLOOKUP(B220,Personal!$A:$A,Personal!$C:$C,""),"")} -> 0 | E220: {=IFERROR(_xlfn.XLOOKUP(D220,Locales!$A:$A,Locales!$B:$B,""),"")} | F220: {=IFERROR(_xlfn.XLOOKUP(B220,Personal!$A:$A,Personal!$F:$F,""),"")} -> 0 | I220: {=IFERROR(INDEX(Precios!$D:$F,MATCH(N220, Precios!$G:$G, 0),CHOOSE(MATCH(H220, {"SML";"XL";"XXL"}, 0), 1, 2, 3)), 0)} -> 0 | K220: =IFERROR(I220*J220,0) -> 0 | N220: =IF( OR(E220="",F220="",G220=""), "",CLEAN(TRIM(E220)) & "|" & CLEAN(TRIM(F220)) & "|" & CLEAN(TRIM(G220))) | O220: =IF(N220="","",IF(COUNTIF(Precios!$G:$G,N220)=0,"⚠ No coincide con Precios","OK"))
C221: {=IFERROR(_xlfn.XLOOKUP(B221,Personal!$A:$A,Personal!$D:$D,""),"")} -> 0 | D221: {=IFERROR(_xlfn.XLOOKUP(B221,Personal!$A:$A,Personal!$C:$C,""),"")} -> 0 | E221: {=IFERROR(_xlfn.XLOOKUP(D221,Locales!$A:$A,Locales!$B:$B,""),"")} | F221: {=IFERROR(_xlfn.XLOOKUP(B221,Personal!$A:$A,Personal!$F:$F,""),"")} -> 0 | I221: {=IFERROR(INDEX(Precios!$D:$F,MATCH(N221, Precios!$G:$G, 0),CHOOSE(MATCH(H221, {"SML";"XL";"XXL"}, 0), 1, 2, 3)), 0)} -> 0 | K221: =IFERROR(I221*J221,0) -> 0 | N221: =IF( OR(E221="",F221="",G221=""), "",CLEAN(TRIM(E221)) & "|" & CLEAN(TRIM(F221)) & "|" & CLEAN(TRIM(G221))) | O221: =IF(N221="","",IF(COUNTIF(Precios!$G:$G,N221)=0,"⚠ No coincide con Precios","OK"))
C222: {=IFERROR(_xlfn.XLOOKUP(B222,Personal!$A:$A,Personal!$D:$D,""),"")} -> 0 | D222: {=IFERROR(_xlfn.XLOOKUP(B222,Personal!$A:$A,Personal!$C:$C,""),"")} -> 0 | E222: {=IFERROR(_xlfn.XLOOKUP(D222,Locales!$A:$A,Locales!$B:$B,""),"")} | F222: {=IFERROR(_xlfn.XLOOKUP(B222,Personal!$A:$A,Personal!$F:$F,""),"")} -> 0 | I222: {=IFERROR(INDEX(Precios!$D:$F,MATCH(N222, Precios!$G:$G, 0),CHOOSE(MATCH(H222, {"SML";"XL";"XXL"}, 0), 1, 2, 3)), 0)} -> 0 | K222: =IFERROR(I222*J222,0) -> 0 | N222: =IF( OR(E222="",F222="",G222=""), "",CLEAN(TRIM(E222)) & "|" & CLEAN(TRIM(F222)) & "|" & CLEAN(TRIM(G222))) | O222: =IF(N222="","",IF(COUNTIF(Precios!$G:$G,N222)=0,"⚠ No coincide con Precios","OK"))
C223: {=IFERROR(_xlfn.XLOOKUP(B223,Personal!$A:$A,Personal!$D:$D,""),"")} -> 0 | D223: {=IFERROR(_xlfn.XLOOKUP(B223,Personal!$A:$A,Personal!$C:$C,""),"")} -> 0 | E223: {=IFERROR(_xlfn.XLOOKUP(D223,Locales!$A:$A,Locales!$B:$B,""),"")} | F223: {=IFERROR(_xlfn.XLOOKUP(B223,Personal!$A:$A,Personal!$F:$F,""),"")} -> 0 | I223: {=IFERROR(INDEX(Precios!$D:$F,MATCH(N223, Precios!$G:$G, 0),CHOOSE(MATCH(H223, {"SML";"XL";"XXL"}, 0), 1, 2, 3)), 0)} -> 0 | K223: =IFERROR(I223*J223,0) -> 0 | N223: =IF( OR(E223="",F223="",G223=""), "",CLEAN(TRIM(E223)) & "|" & CLEAN(TRIM(F223)) & "|" & CLEAN(TRIM(G223))) | O223: =IF(N223="","",IF(COUNTIF(Precios!$G:$G,N223)=0,"⚠ No coincide con Precios","OK"))
C224: {=IFERROR(_xlfn.XLOOKUP(B224,Personal!$A:$A,Personal!$D:$D,""),"")} -> 0 | D224: {=IFERROR(_xlfn.XLOOKUP(B224,Personal!$A:$A,Personal!$C:$C,""),"")} -> 0 | E224: {=IFERROR(_xlfn.XLOOKUP(D224,Locales!$A:$A,Locales!$B:$B,""),"")} | F224: {=IFERROR(_xlfn.XLOOKUP(B224,Personal!$A:$A,Personal!$F:$F,""),"")} -> 0 | I224: {=IFERROR(INDEX(Precios!$D:$F,MATCH(N224, Precios!$G:$G, 0),CHOOSE(MATCH(H224, {"SML";"XL";"XXL"}, 0), 1, 2, 3)), 0)} -> 0 | K224: =IFERROR(I224*J224,0) -> 0 | N224: =IF( OR(E224="",F224="",G224=""), "",CLEAN(TRIM(E224)) & "|" & CLEAN(TRIM(F224)) & "|" & CLEAN(TRIM(G224))) | O224: =IF(N224="","",IF(COUNTIF(Precios!$G:$G,N224)=0,"⚠ No coincide con Precios","OK"))
C225: {=IFERROR(_xlfn.XLOOKUP(B225,Personal!$A:$A,Personal!$D:$D,""),"")} -> 0 | D225: {=IFERROR(_xlfn.XLOOKUP(B225,Personal!$A:$A,Personal!$C:$C,""),"")} -> 0 | E225: {=IFERROR(_xlfn.XLOOKUP(D225,Locales!$A:$A,Locales!$B:$B,""),"")} | F225: {=IFERROR(_xlfn.XLOOKUP(B225,Personal!$A:$A,Personal!$F:$F,""),"")} -> 0 | I225: {=IFERROR(INDEX(Precios!$D:$F,MATCH(N225, Precios!$G:$G, 0),CHOOSE(MATCH(H225, {"SML";"XL";"XXL"}, 0), 1, 2, 3)), 0)} -> 0 | K225: =IFERROR(I225*J225,0) -> 0 | N225: =IF( OR(E225="",F225="",G225=""), "",CLEAN(TRIM(E225)) & "|" & CLEAN(TRIM(F225)) & "|" & CLEAN(TRIM(G225))) | O225: =IF(N225="","",IF(COUNTIF(Precios!$G:$G,N225)=0,"⚠ No coincide con Precios","OK"))
C226: {=IFERROR(_xlfn.XLOOKUP(B226,Personal!$A:$A,Personal!$D:$D,""),"")} -> 0 | D226: {=IFERROR(_xlfn.XLOOKUP(B226,Personal!$A:$A,Personal!$C:$C,""),"")} -> 0 | E226: {=IFERROR(_xlfn.XLOOKUP(D226,Locales!$A:$A,Locales!$B:$B,""),"")} | F226: {=IFERROR(_xlfn.XLOOKUP(B226,Personal!$A:$A,Personal!$F:$F,""),"")} -> 0 | I226: {=IFERROR(INDEX(Precios!$D:$F,MATCH(N226, Precios!$G:$G, 0),CHOOSE(MATCH(H226, {"SML";"XL";"XXL"}, 0), 1, 2, 3)), 0)} -> 0 | K226: =IFERROR(I226*J226,0) -> 0 | N226: =IF( OR(E226="",F226="",G226=""), "",CLEAN(TRIM(E226)) & "|" & CLEAN(TRIM(F226)) & "|" & CLEAN(TRIM(G226))) | O226: =IF(N226="","",IF(COUNTIF(Precios!$G:$G,N226)=0,"⚠ No coincide con Precios","OK"))
C227: {=IFERROR(_xlfn.XLOOKUP(B227,Personal!$A:$A,Personal!$D:$D,""),"")} -> 0 | D227: {=IFERROR(_xlfn.XLOOKUP(B227,Personal!$A:$A,Personal!$C:$C,""),"")} -> 0 | E227: {=IFERROR(_xlfn.XLOOKUP(D227,Locales!$A:$A,Locales!$B:$B,""),"")} | F227: {=IFERROR(_xlfn.XLOOKUP(B227,Personal!$A:$A,Personal!$F:$F,""),"")} -> 0 | I227: {=IFERROR(INDEX(Precios!$D:$F,MATCH(N227, Precios!$G:$G, 0),CHOOSE(MATCH(H227, {"SML";"XL";"XXL"}, 0), 1, 2, 3)), 0)} -> 0 | K227: =IFERROR(I227*J227,0) -> 0 | N227: =IF( OR(E227="",F227="",G227=""), "",CLEAN(TRIM(E227)) & "|" & CLEAN(TRIM(F227)) & "|" & CLEAN(TRIM(G227))) | O227: =IF(N227="","",IF(COUNTIF(Precios!$G:$G,N227)=0,"⚠ No coincide con Precios","OK"))
... C3229: {=IFERROR(_xlfn.XLOOKUP(B3229,Personal!$A:$A,Personal!$D:$D,""),"")} -> 0 | D3229: {=IFERROR(_xlfn.XLOOKUP(B3229,Personal!$A:$A,Personal!$C:$C,""),"")} -> 0 | E3229: {=IFERROR(_xlfn.XLOOKUP(D3229,Locales!$A:$A,Locales!$B:$B,""),"")} | F3229: {=IFERROR(_xlfn.XLOOKUP(B3229,Personal!$A:$A,Personal!$F:$F,""),"")} -> 0 | I3229: {=IFERROR(INDEX(Precios!$D:$F,MATCH(N3229, Precios!$G:$G, 0),CHOOSE(MATCH(H3229, {"SML";"XL";"XXL"}, 0), 1, 2, 3)), 0)} -> 0 | K3229: =IFERROR(I3229*J3229,0) -> 0 | N3229: =IF( OR(E3229="",F3229="",G3229=""), "",CLEAN(TRIM(E3229)) & "|" & CLEAN(TRIM(F3229)) & "|" & CLEAN(TRIM(G3229))) | O3229: =IF(N3229="","",IF(COUNTIF(Precios!$G:$G,N3229)=0,"⚠ No coincide con Precios","OK"))

Sheet Descuentos
A1: DNI | B1: RAZON SOCIAL | C1: LOCAL | D1: APELLIDOS Y NOMBRES | E1: CARGO ESTANDAR | F1: FECHA INGRESO | G1: FECHA DE ENTREGA | H1: MONEDA | I1: DESCUENTO
A2: 74415759 | B2: TREND BUSINES S.A.C. | C2: IQUITOS | D2: GONZALES LOZANO JAIME JUNIOR | E2: CAJA | F2: 45733 | G2: 45974 | H2: S/ | I2: 27
A3: 73233227 | B3: TREND BUSINESS S.A.C. | C3: IQUITOS | D3: DEL CASTILLO TELLO JULIA OTILIA | E3: COUNTER | F3: 45870 | G3: 45974 | H3: S/ | I3: 27
A4: 46192476 | B4: TREND BUSINESS S.A.C. | C4: IQUITOS | D4: BABILONIA VEGA LINDA EBONY | E4: COUNTER | F4: 45901 | G4: 45974 | H4: S/ | I4: 27
A5: 77100486 | B5: TREND BUSINESS S.A.C. | C5: IQUITOS | D5: ALVAN ESCOBEDO ROSA DEL CARMEN | E5: COUNTER | F5: 45903 | G5: 45974 | H5: S/ | I5: 27
A6: 43347817 | B6: TREND BUSINES S.A.C. | C6: IQUITOS | D6: SIAS MELENDEZ ROBIN | E6: PRODUCCIÓN / COCINA | F6: 45627 | G6: 45974 | H6: S/ | I6: 106.5
A7: 62814712 | B7: TREND BUSINES S.A.C. | C7: IQUITOS | D7: PACAYA CHOTA MAYCOL | E7: PRODUCCIÓN / COCINA | F7: 45733 | G7: 45974 | H7: S/ | I7: 106.5
A8: 74415806 | B8: TREND BUSINESS S.A.C. | C8: IQUITOS | D8: FLORES SAQUIRAY MOISES | E8: PRODUCCIÓN / COCINA | F8: 45824 | G8: 45974 | H8: S/ | I8: 106.5
A9: 62814713 | B9: TREND BUSINESS S.A.C. | C9: IQUITOS | D9: PACAYA CHOTA MARCIAL | E9: PRODUCCIÓN / COCINA | F9: 45908 | G9: 45974 | H9: S/ | I9: 106.5
A10: 42792686 | B10: VILLA INVEST S.A.C. | C10: IQUITOS | D10: BARDALES PASMIÑO DANNY AGUSTIN | E10: PRODUCCIÓN / COCINA | F10: 45505 | G10: 45974 | H10: S/ | I10: 106.5
A11: 42949350 | B11: TREND BUSINES S.A.C. | C11: IQUITOS | D11: PANDURO VELA MARCO ANTONIO | E11: PRODUCCIÓN / COCINA | F11: 45661 | G11: 45974 | H11: S/ | I11: 106.5
A12: 43446883 | B12: TREND BUSINES S.A.C. | C12: IQUITOS | D12: TORRES REATEGUI RICHARD JACKSON | E12: MOTORIZADO | F12: 45792 | G12: 45974 | H12: S/ | I12: 27
A13: 45038713 | B13: TREND BUSINES S.A.C. | C13: IQUITOS | D13: COTRINA CARDENAS MARIO GERMAN | E13: STAFF ADMINISTRATIVO | F13: 45616 | G13: 45974 | H13: S/ | I13: 30
... A68: 46831171 | B68: VILLA CHICKEN S.A.C. | C68: VCH-ADM | D68: SANCHEZ LLOCLLA ROGER YAISON | E68: BAR | F68: 45474 | G68: 46010 | H68: S/ | I68: 87

Sheet Movimientos
A1: Fecha | B1: Tipo | C1: LOCAL | D1: GRUPO | E1: CARGO ESTANDAR | F1: MATERIAL | G1: TALLA | H1: Doc/Ref | I1: DNI | J1: Entrada | K1: Salida | L1: Precio Unit | M1: Importe | N1: Obs | O1: Saldo (calc)
A2: 45974 | B2: SALIDA | C2: IQUITOS | D2: PATIO DE COMIDA | E2: CAJA | F2: POLO PIQUÉ CONCHE VINO, MANGA CORTA CAJA | G2: SML | I2: 74415759 | J2: 0 | K2: 2 | L2: 13.5 | M2: -27 | N2: Entrega
A3: 45974 | B3: SALIDA | C3: IQUITOS | D3: PATIO DE COMIDA | E3: COUNTER | F3: POLO PIQUÉ CONCHE VINO, MANGA CORTA COUNTER | G3: SML | I3: 73233227 | J3: 0 | K3: 2 | L3: 13.5 | M3: -27 | N3: Entrega
A4: 45974 | B4: SALIDA | C4: IQUITOS | D4: PATIO DE COMIDA | E4: COUNTER | F4: POLO PIQUÉ CONCHE VINO, MANGA CORTA COUNTER | G4: SML | I4: 46192476 | J4: 0 | K4: 2 | L4: 13.5 | M4: -27 | N4: Entrega
A5: 45974 | B5: SALIDA | C5: IQUITOS | D5: PATIO DE COMIDA | E5: COUNTER | F5: POLO PIQUÉ CONCHE VINO, MANGA CORTA COUNTER | G5: SML | I5: 77100486 | J5: 0 | K5: 2 | L5: 13.5 | M5: -27 | N5: Entrega
A6: 45974 | B6: SALIDA | C6: IQUITOS | D6: PATIO DE COMIDA | E6: PRODUCCIÓN / COCINA | F6: CHAQUETA DRILL BLANCO | G6: SML | I6: 43347817 | J6: 0 | K6: 2 | L6: 16.25 | M6: -32.5 | N6: Entrega
A7: 45974 | B7: SALIDA | C7: IQUITOS | D7: PATIO DE COMIDA | E7: PRODUCCIÓN / COCINA | F7: PANTALÓN SAL Y PIMIENTA | G7: SML | I7: 43347817 | J7: 0 | K7: 2 | L7: 11 | M7: -22 | N7: Entrega
A8: 45974 | B8: SALIDA | C8: IQUITOS | D8: PATIO DE COMIDA | E8: PRODUCCIÓN / COCINA | F8: PECHERA GRIS EN DRILL | G8: SML | I8: 43347817 | J8: 0 | K8: 2 | L8: 6.5 | M8: -13 | N8: Entrega
A9: 45974 | B9: SALIDA | C9: IQUITOS | D9: PATIO DE COMIDA | E9: PRODUCCIÓN / COCINA | F9: GARIBALDI GRIS | G9: SML | I9: 43347817 | J9: 0 | K9: 2 | L9: 4.5 | M9: -9 | N9: Entrega
A10: 45974 | B10: SALIDA | C10: IQUITOS | D10: PATIO DE COMIDA | E10: PRODUCCIÓN / COCINA | F10: POLO 30/1 GRIS | G10: SML | I10: 43347817 | J10: 0 | K10: 4 | L10: 7.5 | M10: -30 | N10: Entrega
A11: 45974 | B11: SALIDA | C11: IQUITOS | D11: PATIO DE COMIDA | E11: PRODUCCIÓN / COCINA | F11: CHAQUETA DRILL BLANCO | G11: SML | I11: 62814712 | J11: 0 | K11: 2 | L11: 16.25 | M11: -32.5 | N11: Entrega
A12: 45974 | B12: SALIDA | C12: IQUITOS | D12: PATIO DE COMIDA | E12: PRODUCCIÓN / COCINA | F12: PANTALÓN SAL Y PIMIENTA | G12: SML | I12: 62814712 | J12: 0 | K12: 2 | L12: 11 | M12: -22 | N12: Entrega
A13: 45974 | B13: SALIDA | C13: IQUITOS | D13: PATIO DE COMIDA | E13: PRODUCCIÓN / COCINA | F13: PECHERA GRIS EN DRILL | G13: SML | I13: 62814712 | J13: 0 | K13: 2 | L13: 6.5 | M13: -13 | N13: Entrega
... A215: 46010 | B215: SALIDA | C215: VCH-ADM | D215: LIMA E ICA PROVINCIA | E215: BAR | F215: POLO 30/1 GRIS | G215: SML | I215: 46831171 | J215: 0 | K215: 2 | L215: 7.5 | M215: -15 | N215: Entrega

Sheet Stock
A1: GRUPO | B1: CARGO ESTANDAR | C1: MATERIAL | D1: TALLA | E1: Entradas | F1: Salidas | G1: Ajuste | H1: Disponible
A2: LIMA E ICA PROVINCIA | B2: MOTORIZADO | C2: POLO PIQUÉ PLOMO, MANGA LARGA MOTORIZADO | D2: SML | E2: 0 | F2: 26 | G2: 0 | H2: -26
A3: LIMA E ICA PROVINCIA | B3: MOTORIZADO | C3: GORRO NEGRO MOTORIZADO | D3: SML | E3: 0 | F3: 20 | G3: 0 | H3: -20
A4: LIMA E ICA PROVINCIA | B4: MOTORIZADO | C4: CASACA NEGRA CON REFLECTIVOS MOTORIZADO | D4: SML | E4: 0 | F4: 18 | G4: 0 | H4: -18
A5: LIMA E ICA PROVINCIA | B5: MOTORIZADO | C5: POLO PIQUÉ PLOMO, MANGA LARGA MOTORIZADO | D5: XL | E5: 0 | F5: 4 | G5: 0 | H5: -4
A6: LIMA E ICA PROVINCIA | B6: MOTORIZADO | C6: GORRO NEGRO MOTORIZADO | D6: XL | E6: 0 | F6: 4 | G6: 0 | H6: -4
A7: LIMA E ICA PROVINCIA | B7: MOTORIZADO | C7: CASACA NEGRA CON REFLECTIVOS MOTORIZADO | D7: XL | E7: 0 | F7: 2 | G7: 0 | H7: -2
A8: LIMA E ICA PROVINCIA | B8: AZAFATA | C8: BLUSA BLANCA (MANGA LARGA) | D8: SML | E8: 0 | F8: 36 | G8: 0 | H8: -36
A9: LIMA E ICA PROVINCIA | B9: AZAFATA | C9: MANDILON DRILL NEGRO | D9: SML | E9: 0 | F9: 28 | G9: 0 | H9: -28
A10: LIMA E ICA PROVINCIA | B10: AZAFATA | C10: ANDARIN GRANATE | D10: SML | E10: 0 | F10: 24 | G10: 0 | H10: -24
A11: LIMA E ICA PROVINCIA | B11: MOZO | C11: CAMISA BLANCA (MANGA LARGA) | D11: SML | E11: 0 | F11: 77 | G11: 0 | H11: -77
A12: LIMA E ICA PROVINCIA | B12: MOZO | C12: MANDILON DRILL NEGRO | D12: SML | E12: 0 | F12: 65 | G12: 0 | H12: -65
A13: LIMA E ICA PROVINCIA | B13: MOZO | C13: ANDARIN GRANATE | D13: SML | E13: 0 | F13: 60 | G13: 0 | H13: -60
... A102: LIMA E ICA PROVINCIA | B102: PRODUCCIÓN / COCINA | C102: POLO 30/1 GRIS | D102: XXL | E102: 0 | F102: 2 | G102: 0 | H102: -2

Sheet Resumen
A1: Panel
A3: Total a descontar (S/) | B3: =SUMIF(Solicitudes!$L:$L,"ENTREGADO",Solicitudes!$K:$K) -> 4687
A5: Filtra 'Solicitudes' por DNI para ver el histórico por persona. El stock se calcula por GRUPO+CARGO+MATERIAL+TALLA.
